Workbook

Sheet COLLECTION PRICE
A1: Current prices - 2024
B2: Instalments | C2: ST | D2: PR | E2: ST+TK | F2: PR+TK | G2: PL1 | H2: Tkanivo placenty | I2: Tkanivo pupocnika | J2: Inflation rate 2024 | K2: FX rate
A3: SK | B3: 1 | C3: 690 | D3: 890 | E3: 990 | F3: 1190 | G3: 1490 | K3: 1
B4: 5 | C4: =+C3 -> 690 | D4: =+D3 -> 890 | E4: =+E3 -> 990 | F4: =+F3 -> 1190 | G4: =+G3 -> 1490
B5: 10 | C5: =+C4 -> 690 | D5: =+D4 -> 890 | E5: =+E4 -> 990 | F5: =+F4 -> 1190 | G5: =+G4 -> 1490
A6: RO | B6: 1 | C6: 2490 | D6: 3590 | E6: 3490 | F6: 4590 | G6: 9990 | K6: 5
B7: 3 | C7: 2739 | D7: 3771 | E7: 3789 | F7: 4821 | G7: 10490
B8: 12 | C8: 2988 | D8: 3948 | E8: 4092 | F8: 5052 | G8: 10990
A9: HU | B9: 1 | C9: 149000 | D9: 249000 | E9: 248000 | F9: 348000 | K9: 400
B10: 3 | C10: =+C9 -> 149000 | D10: =+D9 -> 249000 | E10: =+E9 -> 248000 | F10: =+F9 -> 348000 | G10: =+G9 -> 0
B11: 12 | C11: =+C10 -> 149000 | D11: =+D10 -> 249000 | E11: =+E10 -> 248000 | F11: =+F10 -> 348000 | G11: =+G10 -> 0
A12: CZ | B12: 1 | C12: 19900 | D12: 29900 | E12: 29900 | F12: 39900 | G12: 49900 | K12: 25
B13: 5 | C13: =+C12 -> 19900 | D13: =+D12 -> 29900 | E13: =+E12 -> 29900 | F13: =+F12 -> 39900 | G13: =+G12 -> 49900
B14: 10 | C14: =+C13 -> 19900 | D14: =+D13 -> 29900 | E14: =+E13 -> 29900 | F14: =+F13 -> 39900 | G14: =+G13 -> 49900
A15: AT | B15: 1 | C15: 1490 | D15: 1790 | E15: 2190 | F15: 2490 | K15: 1
B16: 4 | C16: =+C15 -> 1490 | D16: =+D15 -> 1790 | E16: =+E15 -> 2190 | F16: =+F15 -> 2490 | G16: =+G15 -> 0
B17: 8 | C17: =+C16 -> 1490 | D17: =+D16 -> 1790 | E17: =+E16 -> 2190 | F17: =+F16 -> 2490 | G17: =+G16 -> 0
A18: IT | B18: 1 | C18: 1090 | D18: 1290 | E18: 1390 | F18: 1590 | K18: 1
B19: 3 | C19: =+C18 -> 1090 | D19: =+D18 -> 1290 | E19: =+E18 -> 1390 | F19: =+F18 -> 1590 | G19: =+G18 -> 0
B20: 6 | C20: =+C19 -> 1090 | D20: =+D19 -> 1290 | E20: =+E19 -> 1390 | F20: =+F19 -> 1590 | G20: =+G19 -> 0
A23: New prices - local CCY - 2025 | J23: Instalment increase
B24: Instalments | C24: ST | D24: PR | E24: ST+TK | F24: PR+TK | G24: PL1 | H24: Tkanivo placenty | I24: Tkanivo pupocnika
A25: SK | B25: 1 | C25: 1400 | D25: 1600 | E25: 1800 | F25: 2100 | G25: 2500 | H25: 1600 | I25: 1200
B26: 3 | C26: =+C25*(1+$J26) -> 1400 | D26: =+D25*(1+$J26) -> 1600 | E26: =+E25*(1+$J26) -> 1800 | F26: =+F25*(1+$J26) -> 2100 | G26: =+G25*(1+$J26) -> 2500 | H26: =+H25*(1+$J26) -> 1600 | I26: =+I25*(1+$J26) -> 1200 | J26: 0
B27: 12 | C27: =+C25*(1+$J27) -> 1400 | D27: =+D25*(1+$J27) -> 1600 | E27: =+E25*(1+$J27) -> 1800 | F27: =+F25*(1+$J27) -> 2100 | G27: =+G25*(1+$J27) -> 2500 | H27: =+H25*(1+$J27) -> 1600 | I27: =+I25*(1+$J27) -> 1200 | J27: 0
A28: RO | B28: 1 | C28: =1400*$K$6 -> 7000 | D28: =1600*$K$6 -> 8000 | E28: =1800*$K$6 -> 9000 | F28: =2100*$K$6 -> 10500 | G28: =2500*$K$6 -> 12500 | H28: 8000 | I28: 3000
B29: 3 | C29: =+C28*(1+$J29) -> 7000 | D29: =+D28*(1+$J29) -> 8000 | E29: =+E28*(1+$J29) -> 9000 | F29: =+F28*(1+$J29) -> 10500 | G29: =+G28*(1+$J29) -> 12500 | H29: =+H28*(1+$J29) -> 8000 | I29: =+I28*(1+$J29) -> 3000 | J29: 0
B30: 12 | C30: =+C28*(1+$J30) -> 7000 | D30: =+D28*(1+$J30) -> 8000 | E30: =+E28*(1+$J30) -> 9000 | F30: =+F28*(1+$J30) -> 10500 | G30: =+G28*(1+$J30) -> 12500 | H30: =+H28*(1+$J30) -> 8000 | I30: =+I28*(1+$J30) -> 3000 | J30: 0
A31: HU | B31: 1 | C31: =1400*$K$9 -> 560000 | D31: =1600*$K$9 -> 640000 | E31: =1800*$K$9 -> 720000 | F31: =2100*$K$9 -> 840000 | I31: 240000
B32: 3 | C32: =+C31*(1+$J32) -> 560000 | D32: =+D31*(1+$J32) -> 640000 | E32: =+E31*(1+$J32) -> 720000 | F32: =+F31*(1+$J32) -> 840000 | I32: =+I31*(1+$J32) -> 240000 | J32: 0
B33: 12 | C33: =+C31*(1+$J33) -> 560000 | D33: =+D31*(1+$J33) -> 640000 | E33: =+E31*(1+$J33) -> 720000 | F33: =+F31*(1+$J33) -> 840000 | I33: =+I31*(1+$J33) -> 240000 | J33: 0
A34: CZ | B34: 1 | C34: =1400*$K$12 -> 35000 | D34: =1600*$K$12 -> 40000 | E34: =1800*$K$12 -> 45000 | F34: =2100*$K$12 -> 52500 | G34: =2500*$K$12 -> 62500 | H34: 40000 | I34: 30000
B35: 3 | C35: =+C34*(1+$J35) -> 35000 | D35: =+D34*(1+$J35) -> 40000 | E35: =+E34*(1+$J35) -> 45000 | F35: =+F34*(1+$J35) -> 52500 | G35: =+G34*(1+$J35) -> 62500 | H35: =+H34*(1+$J35) -> 40000 | I35: =+I34*(1+$J35) -> 30000 | J35: 0
B36: 12 | C36: =+C34*(1+$J36) -> 35000 | D36: =+D34*(1+$J36) -> 40000 | E36: =+E34*(1+$J36) -> 45000 | F36: =+F34*(1+$J36) -> 52500 | G36: =+G34*(1+$J36) -> 62500 | H36: =+H34*(1+$J36) -> 40000 | I36: =+I34*(1+$J36) -> 30000 | J36: 0
A37: AT | B37: 1 | C37: =+C15 -> 1490 | D37: =+D15 -> 1790 | E37: =+E15 -> 2190 | F37: =+F15 -> 2490 | G37: =+G15 -> 0 | H37: =+H15 -> 0 | I37: 1200
B38: 4 | C38: =+C37*(1+$J38) -> 1490 | D38: =+D37*(1+$J38) -> 1790 | E38: =+E37*(1+$J38) -> 2190 | F38: =+F37*(1+$J38) -> 2490 | G38: =+G37*(1+$J38) -> 0 | H38: =+H37*(1+$J38) -> 0 | I38: =+I37*(1+$J38) -> 1200 | J38: 0
B39: 8 | C39: =+C37*(1+$J39) -> 1490 | D39: =+D37*(1+$J39) -> 1790 | E39: =+E37*(1+$J39) -> 2190 | F39: =+F37*(1+$J39) -> 2490 | G39: =+G37*(1+$J39) -> 0 | H39: =+H37*(1+$J39) -> 0 | I39: =+I37*(1+$J39) -> 1200 | J39: 0
A40: IT | B40: 1 | C40: =+C18 -> 1090 | D40: =+D18 -> 1290 | E40: =+E18 -> 1390 | F40: =+F18 -> 1590 | G40: =+G18 -> 0 | H40: =+H18 -> 0 | I40: 300
B41: 3 | C41: =+C40*(1+$J41) -> 1090 | D41: =+D40*(1+$J41) -> 1290 | E41: =+E40*(1+$J41) -> 1390 | F41: =+F40*(1+$J41) -> 1590 | G41: =+G40*(1+$J41) -> 0 | H41: =+H40*(1+$J41) -> 0 | I41: =+I40*(1+$J41) -> 300 | J41: 0
B42: 6 | C42: =+C40*(1+$J42) -> 1090 | D42: =+D40*(1+$J42) -> 1290 | E42: =+E40*(1+$J42) -> 1390 | F42: =+F40*(1+$J42) -> 1590 | G42: =+G40*(1+$J42) -> 0 | H42: =+H40*(1+$J42) -> 0 | I42: =+I40*(1+$J42) -> 300 | J42: 0
A44: New prices - EUR - 2025
B45: Years | C45: ST | D45: PR | E45: ST+TK | F45: PR+TK | G45: PL1 | H45: Tkanivo placenty | I45: Tkanivo pupocnika
A46: SK | B46: =+B25 -> 1 | C46: =+C25/$K$3 -> 1400 | D46: =+D25/$K$3 -> 1600 | E46: =+E25/$K$3 -> 1800 | F46: =+F25/$K$3 -> 2100 | G46: =+G25/$K$3 -> 2500 | H46: =+H25/$K$3 -> 1600 | I46: =+I25/$K$3 -> 1200
B47: =+B26 -> 3 | C47: =+C26/$K$3 -> 1400 | D47: =+D26/$K$3 -> 1600 | E47: =+E26/$K$3 -> 1800 | F47: =+F26/$K$3 -> 2100 | G47: =+G26/$K$3 -> 2500 | H47: =+H26/$K$3 -> 1600 | I47: =+I26/$K$3 -> 1200
B48: =+B27 -> 12 | C48: =+C27/$K$3 -> 1400 | D48: =+D27/$K$3 -> 1600 | E48: =+E27/$K$3 -> 1800 | F48: =+F27/$K$3 -> 2100 | G48: =+G27/$K$3 -> 2500 | H48: =+H27/$K$3 -> 1600 | I48: =+I27/$K$3 -> 1200
A49: RO | B49: =+B28 -> 1 | C49: =+C28/$K$6 -> 1400 | D49: =+D28/$K$6 -> 1600 | E49: =+E28/$K$6 -> 1800 | F49: =+F28/$K$6 -> 2100 | G49: =+G28/$K$6 -> 2500 | H49: =+H28/$K$6 -> 1600 | I49: =+I28/$K$6 -> 600
B50: =+B29 -> 3 | C50: =+C29/$K$6 -> 1400 | D50: =+D29/$K$6 -> 1600 | E50: =+E29/$K$6 -> 1800 | F50: =+F29/$K$6 -> 2100 | G50: =+G29/$K$6 -> 2500 | H50: =+H29/$K$6 -> 1600 | I50: =+I29/$K$6 -> 600
B51: =+B30 -> 12 | C51: =+C30/$K$6 -> 1400 | D51: =+D30/$K$6 -> 1600 | E51: =+E30/$K$6 -> 1800 | F51: =+F30/$K$6 -> 2100 | G51: =+G30/$K$6 -> 2500 | H51: =+H30/$K$6 -> 1600 | I51: =+I30/$K$6 -> 600
A52: HU | B52: =+B31 -> 1 | C52: =+C31/$K$9 -> 1400 | D52: =+D31/$K$9 -> 1600 | E52: =+E31/$K$9 -> 1800 | F52: =+F31/$K$9 -> 2100 | G52: =+G31/$K$9 -> 0 | H52: =+H31/$K$9 -> 0 | I52: =+I31/$K$9 -> 600
B53: =+B32 -> 3 | C53: =+C32/$K$9 -> 1400 | D53: =+D32/$K$9 -> 1600 | E53: =+E32/$K$9 -> 1800 | F53: =+F32/$K$9 -> 2100 | G53: =+G32/$K$9 -> 0 | H53: =+H32/$K$9 -> 0 | I53: =+I32/$K$9 -> 600
B54: =+B33 -> 12 | C54: =+C33/$K$9 -> 1400 | D54: =+D33/$K$9 -> 1600 | E54: =+E33/$K$9 -> 1800 | F54: =+F33/$K$9 -> 2100 | G54: =+G33/$K$9 -> 0 | H54: =+H33/$K$9 -> 0 | I54: =+I33/$K$9 -> 600
A55: CZ | B55: =+B34 -> 1 | C55: =+C34/$K$12 -> 1400 | D55: =+D34/$K$12 -> 1600 | E55: =+E34/$K$12 -> 1800 | F55: =+F34/$K$12 -> 2100 | G55: =+G34/$K$12 -> 2500 | H55: =+H34/$K$12 -> 1600 | I55: =+I34/$K$12 -> 1200
B56: =+B35 -> 3 | C56: =+C35/$K$12 -> 1400 | D56: =+D35/$K$12 -> 1600 | E56: =+E35/$K$12 -> 1800 | F56: =+F35/$K$12 -> 2100 | G56: =+G35/$K$12 -> 2500 | H56: =+H35/$K$12 -> 1600 | I56: =+I35/$K$12 -> 1200
B57: =+B36 -> 12 | C57: =+C36/$K$12 -> 1400 | D57: =+D36/$K$12 -> 1600 | E57: =+E36/$K$12 -> 1800 | F57: =+F36/$K$12 -> 2100 | G57: =+G36/$K$12 -> 2500 | H57: =+H36/$K$12 -> 1600 | I57: =+I36/$K$12 -> 1200
A58: AT | B58: =+B37 -> 1 | C58: =+C37/$K$15 -> 1490 | D58: =+D37/$K$15 -> 1790 | E58: =+E37/$K$15 -> 2190 | F58: =+F37/$K$15 -> 2490 | I58: =+I37/$K$15 -> 1200
B59: =+B38 -> 4 | C59: =+C38/$K$15 -> 1490 | D59: =+D38/$K$15 -> 1790 | E59: =+E38/$K$15 -> 2190 | F59: =+F38/$K$15 -> 2490 | I59: =+I38/$K$15 -> 1200
B60: =+B39 -> 8 | C60: =+C39/$K$15 -> 1490 | D60: =+D39/$K$15 -> 1790 | E60: =+E39/$K$15 -> 2190 | F60: =+F39/$K$15 -> 2490 | I60: =+I39/$K$15 -> 1200
A61: IT | B61: =+B40 -> 1 | C61: =+C40/$K$18 -> 1090 | D61: =+D40/$K$18 -> 1290 | E61: =+E40/$K$18 -> 1390 | F61: =+F40/$K$18 -> 1590 | I61: =+I40/$K$18 -> 300
B62: =+B41 -> 3 | C62: =+C41/$K$18 -> 1090 | D62: =+D41/$K$18 -> 1290 | E62: =+E41/$K$18 -> 1390 | F62: =+F41/$K$18 -> 1590 | I62: =+I41/$K$18 -> 300
B63: =+B42 -> 6 | C63: =+C42/$K$18 -> 1090 | D63: =+D42/$K$18 -> 1290 | E63: =+E42/$K$18 -> 1390 | F63: =+F42/$K$18 -> 1590 | I63: =+I42/$K$18 -> 300

Sheet STORAGE PRICE
A1: Current basic prices - PY - 2025
B2: Years | C2: ST | D2: PR | E2: ST+TK | F2: PR+TK | G2: PL1 | H2: Tkanivo placenty | I2: Tkanivo pupocnika | J2: Inflation rate 2025 | K2: FX rate
A3: SK | B3: 1 | C3: 80.663099 | D3: 92.567751 | E3: 102.21188 | F3: 114.11653 | G3: 197.02879 | H3: 0 | I3: 21.548782 | J3: 0.04 | K3: 1
B4: 10 | C4: 685.63067 | D4: 786.79748 | E4: 868.84643 | F4: 970.00188 | G4: 1674.7504 | H4: 0 | I4: 183.2044 | J4: 0.04 | K4: 1
B5: 20 | C5: 1209.9465 | D5: 1388.4595 | E5: 1533.2464 | F5: 1711.7707 | G5: 2955.4319 | H5: 0 | I5: 323.31124 | J5: 0.04 | K5: 1
A6: RO | B6: 1 | C6: 360 | D6: 490 | E6: 490 | F6: 620 | G6: 1050 | H6: 430 | I6: 130 | J6: 0.073 | K6: 5.0424
B7: 10 | C7: 3060 | D7: 4165 | E7: 4165 | F7: 5270 | G7: 8925 | H7: 3655 | I7: 1105 | J7: 0.073 | K7: 5.0424
B8: 20 | C8: 5400 | D8: 7350 | E8: 7350 | F8: 9300 | G8: 15750 | H8: 6450 | I8: 1950 | J8: 0.073 | K8: 5.0424
A9: HU | B9: 1 | C9: 30770 | D9: 39740 | E9: 38450 | F9: 47420 | G9: 0 | H9: 0 | I9: 7685 | J9: 0.044 | K9: 397.7675
B10: 10 | C10: 184620 | D10: 238440 | E10: 230700 | F10: 284520 | G10: 0 | H10: 0 | I10: 46100 | J10: 0.044 | K10: 397.7675
B11: 20 | C11: 307700 | D11: 397400 | E11: 384500 | F11: 474200 | G11: 0 | H11: 0 | I11: 76835 | J11: 0.044 | K11: 397.7675
A12: HU splatky | B12: 10 | I12: 11530 | J12: 0.044 | K12: 397.7675
B13: 20 | I13: 19215 | J13: 0.044 | K13: 397.7675
A14: CZ | B14: 1 | C14: 2182 | D14: 2730 | E14: 3605 | F14: 4152 | G14: 4932 | H14: 0 | I14: 0 | J14: 0.025 | K14: 24.6879
B15: 5 | C15: 9819 | D15: 12285 | E15: 16222.5 | F15: 18684 | G15: 22191 | H15: 0 | I15: 0 | J15: 0.025 | K15: 24.6879
B16: 10 | C16: 18547 | D16: 23205 | E16: 30642.5 | F16: 35292 | G16: 41915 | H16: 0 | I16: 0 | J16: 0.025 | K16: 24.6879
A17: AT | B17: 1 | C17: 65.446458 | D17: 76.539078 | E17: 87.631698 | F17: 98.724318 | G17: 0 | H17: 0 | I17: 76.539078 | J17: 0.036 | K17: 1 | L17: AT, IT: the annual rate of inflation is to be taken into account for an annual increase by more than 5%
B18: 5 | C18: 310.59336 | D18: 363.83794 | E18: 415.97325 | F18: 469.21783 | G18: 0 | H18: 0 | I18: 363.83794 | J18: 0.036 | K18: 1
B19: 10 | C19: 589.01812 | D19: 688.8517 | E19: 788.68528 | F19: 888.51886 | G19: 0 | H19: 0 | I19: 688.8517 | J19: 0.036 | K19: 1
A20: IT | B20: 1 | C20: 64.0542 | D20: 85.4056 | E20: 85.4056 | F20: 90.74345 | G20: 0 | H20: 0 | I20: 0 | J20: 0.015 | K20: 1 | L20: AT, IT: the annual rate of inflation is to be taken into account for an annual increase by more than 5%
B21: 10 | C21: 533.785 | D21: 629.8663 | E21: 715.2719 | F21: 747.299 | G21: 0 | H21: 0 | I21: 0 | J21: 0.015 | K21: 1
B22: 20 | C22: 960.813 | D22: 1067.57 | E22: 1174.327 | F22: 1281.084 | G22: 0 | H22: 0 | I22: 0 | J22: 0.015 | K22: 1
A25: Prices after inflation rate impact - local CCY - 2026
B26: Years | C26: ST | D26: PR | E26: ST+TK | F26: PR+TK | G26: PL1 | H26: Tkanivo placenty | I26: Tkanivo pupocnika
A27: SK | B27: 1 | C27: =+C3*(1+$J3) -> 83.889623 | D27: =+D3*(1+$J3) -> 96.270461 | E27: =+E3*(1+$J3) -> 106.30036 | F27: =+F3*(1+$J3) -> 118.68119 | G27: =+G3*(1+$J3) -> 204.90994 | H27: =+H3*(1+$J3) -> 0 | I27: =+I3*(1+$J3) -> 22.410733
B28: 10 | C28: =+C4*(1+$J4) -> 713.05589 | D28: =+D4*(1+$J4) -> 818.26938 | E28: =+E4*(1+$J4) -> 903.60028 | F28: =+F4*(1+$J4) -> 1008.802 | G28: =+G4*(1+$J4) -> 1741.7404 | H28: =+H4*(1+$J4) -> 0 | I28: =+I4*(1+$J4) -> 190.53258
B29: 20 | C29: =+C5*(1+$J5) -> 1258.3444 | D29: =+D5*(1+$J5) -> 1443.9978 | E29: =+E5*(1+$J5) -> 1594.5762 | F29: =+F5*(1+$J5) -> 1780.2415 | G29: =+G5*(1+$J5) -> 3073.6492 | H29: =+H5*(1+$J5) -> 0 | I29: =+I5*(1+$J5) -> 336.24369
A30: RO | B30: 1 | C30: =+C6*(1+$J6) -> 386.28 | D30: =+D6*(1+$J6) -> 525.77 | E30: =+E6*(1+$J6) -> 525.77 | F30: =+F6*(1+$J6) -> 665.26 | G30: =+G6*(1+$J6) -> 1126.65 | H30: =+H6*(1+$J6) -> 461.39 | I30: =+I6*(1+$J6) -> 139.49
B31: 10 | C31: =+C7*(1+$J7) -> 3283.38 | D31: =+D7*(1+$J7) -> 4469.045 | E31: =+E7*(1+$J7) -> 4469.045 | F31: =+F7*(1+$J7) -> 5654.71 | G31: =+G7*(1+$J7) -> 9576.525 | H31: =+H7*(1+$J7) -> 3921.815 | I31: =+I7*(1+$J7) -> 1185.665
B32: 20 | C32: =+C8*(1+$J8) -> 5794.2 | D32: =+D8*(1+$J8) -> 7886.55 | E32: =+E8*(1+$J8) -> 7886.55 | F32: =+F8*(1+$J8) -> 9978.9 | G32: =+G8*(1+$J8) -> 16899.75 | H32: =+H8*(1+$J8) -> 6920.85 | I32: =+I8*(1+$J8) -> 2092.35
A33: HU | B33: 1 | C33: =+C9*(1+$J9) -> 32123.88 | D33: =+D9*(1+$J9) -> 41488.56 | E33: =+E9*(1+$J9) -> 40141.8 | F33: =+F9*(1+$J9) -> 49506.48 | G33: =+G9*(1+$J9) -> 0 | H33: =+H9*(1+$J9) -> 0 | I33: =+I9*(1+$J9) -> 8023.14
B34: 10 | C34: =+C10*(1+$J10) -> 192743.28 | D34: =+D10*(1+$J10) -> 248931.36 | E34: =+E10*(1+$J10) -> 240850.8 | F34: =+F10*(1+$J10) -> 297038.88 | G34: =+G10*(1+$J10) -> 0 | H34: =+H10*(1+$J10) -> 0 | I34: =+I10*(1+$J10) -> 48128.4
B35: 20 | C35: =+C11*(1+$J11) -> 321238.8 | D35: =+D11*(1+$J11) -> 414885.6 | E35: =+E11*(1+$J11) -> 401418 | F35: =+F11*(1+$J11) -> 495064.8 | G35: =+G11*(1+$J11) -> 0 | H35: =+H11*(1+$J11) -> 0 | I35: =+I11*(1+$J11) -> 80215.74
A36: HU splatky | B36: 10 | I36: =+I12*(1+$J12) -> 12037.32
B37: 20 | I37: =+I13*(1+$J13) -> 20060.46
A38: CZ | B38: 1 | C38: =+C14*(1+$J14) -> 2236.55 | D38: =+D14*(1+$J14) -> 2798.25 | E38: =+E14*(1+$J14) -> 3695.125 | F38: =+F14*(1+$J14) -> 4255.8 | G38: =+G14*(1+$J14) -> 5055.3 | H38: 0 | I38: =+I14*(1+$J14) -> 0
B39: 5 | C39: =+C15*(1+$J15) -> 10064.475 | D39: =+D15*(1+$J15) -> 12592.125 | E39: =+E15*(1+$J15) -> 16628.062 | F39: =+F15*(1+$J15) -> 19151.1 | G39: =+G15*(1+$J15) -> 22745.775 | H39: 0 | I39: =+I15*(1+$J15) -> 0
B40: 10 | C40: =+C16*(1+$J16) -> 19010.675 | D40: =+D16*(1+$J16) -> 23785.125 | E40: =+E16*(1+$J16) -> 31408.562 | F40: =+F16*(1+$J16) -> 36174.3 | G40: =+G16*(1+$J16) -> 42962.875 | H40: 0 | I40: =+I16*(1+$J16) -> 0
A41: AT | B41: 1 | C41: =+C17*(1+$J17) -> 67.80253 | D41: =+D17*(1+$J17) -> 79.294485 | E41: =+E17*(1+$J17) -> 90.786439 | F41: =+F17*(1+$J17) -> 102.27839 | G41: =+G17*(1+$J17) -> 0 | H41: =+H17*(1+$J17) -> 0 | I41: =+I17*(1+$J17) -> 79.294485
B42: 5 | C42: =+C18*(1+$J18) -> 321.77472 | D42: =+D18*(1+$J18) -> 376.9361 | E42: =+E18*(1+$J18) -> 430.94829 | F42: =+F18*(1+$J18) -> 486.10967 | G42: =+G18*(1+$J18) -> 0 | H42: =+H18*(1+$J18) -> 0 | I42: =+I18*(1+$J18) -> 376.9361
B43: 10 | C43: =+C19*(1+$J19) -> 610.22277 | D43: =+D19*(1+$J19) -> 713.65036 | E43: =+E19*(1+$J19) -> 817.07795 | F43: =+F19*(1+$J19) -> 920.50554 | G43: =+G19*(1+$J19) -> 0 | H43: =+H19*(1+$J19) -> 0 | I43: =+I19*(1+$J19) -> 713.65036
A44: IT | B44: 1 | C44: =+C20*(1+$J20) -> 65.015013 | D44: =+D20*(1+$J20) -> 86.686684 | E44: =+E20*(1+$J20) -> 86.686684 | F44: =+F20*(1+$J20) -> 92.104602 | G44: =+G20*(1+$J20) -> 0 | H44: =+H20*(1+$J20) -> 0 | I44: =+I20*(1+$J20) -> 0
B45: 10 | C45: =+C21*(1+$J21) -> 541.79177 | D45: =+D21*(1+$J21) -> 639.31429 | E45: =+E21*(1+$J21) -> 726.00098 | F45: =+F21*(1+$J21) -> 758.50848 | G45: =+G21*(1+$J21) -> 0 | H45: =+H21*(1+$J21) -> 0 | I45: =+I21*(1+$J21) -> 0
B46: 20 | C46: =+C22*(1+$J22) -> 975.22519 | D46: =+D22*(1+$J22) -> 1083.5835 | E46: =+E22*(1+$J22) -> 1191.9419 | F46: =+F22*(1+$J22) -> 1300.3003 | G46: =+G22*(1+$J22) -> 0 | H46: =+H22*(1+$J22) -> 0 | I46: =+I22*(1+$J22) -> 0
A48: Prices after inflation rate impact - local CCY - rounding - 2026
B49: Years | C49: ST | D49: PR | E49: ST+TK | F49: PR+TK | G49: PL1 | H49: Tkanivo placenty | I49: Tkanivo pupocnika
A50: SK | B50: 1 | C50: =+C27 -> 83.889623 | D50: =+D27 -> 96.270461 | E50: =+E27 -> 106.30036 | F50: =+F27 -> 118.68119 | G50: =+G27 -> 204.90994 | H50: =+H27 -> 0 | I50: =+I27 -> 22.410733
B51: 10 | C51: =+C28 -> 713.05589 | D51: =+D28 -> 818.26938 | E51: =+E28 -> 903.60028 | F51: =+F28 -> 1008.802 | G51: =+G28 -> 1741.7404 | H51: =+H28 -> 0 | I51: =+I28 -> 190.53258
B52: 20 | C52: =+C29 -> 1258.3444 | D52: =+D29 -> 1443.9978 | E52: =+E29 -> 1594.5762 | F52: =+F29 -> 1780.2415 | G52: =+G29 -> 3073.6492 | H52: =+H29 -> 0 | I52: =+I29 -> 336.24369
A53: RO | B53: 1 | C53: =_xlfn.CEILING.MATH(ROUND(C30,-1),10) -> 390 | D53: =_xlfn.CEILING.MATH(ROUND(D30,-1),10) -> 530 | E53: =_xlfn.CEILING.MATH(ROUND(E30,-1),10) -> 530 | F53: =_xlfn.CEILING.MATH(ROUND(F30,-1),10) -> 670 | G53: =_xlfn.CEILING.MATH(ROUND(G30,-1),10) -> 1130 | H53: =_xlfn.CEILING.MATH(ROUND(H30,-1),10) -> 460 | I53: =_xlfn.CEILING.MATH(ROUND(I30,-1),10) -> 140
B54: 10 | C54: =(C53*10)*85% -> 3315 | D54: =(D53*10)*85% -> 4505 | E54: =(E53*10)*85% -> 4505 | F54: =(F53*10)*85% -> 5695 | G54: =(G53*10)*85% -> 9605 | H54: =(H53*10)*85% -> 3910 | I54: =(I53*10)*85% -> 1190
B55: 20 | C55: =(C53*20)*75% -> 5850 | D55: =(D53*20)*75% -> 7950 | E55: =(E53*20)*75% -> 7950 | F55: =(F53*20)*75% -> 10050 | G55: =(G53*20)*75% -> 16950 | H55: =(H53*20)*75% -> 6900 | I55: =(I53*20)*75% -> 2100
A56: HU | B56: 1 | C56: =IF(MID(ROUNDDOWN(C33,0),LEN(ROUNDDOWN(C33,0)),1)="5",ROUNDDOWN(C33,0),ROUND(ROUNDDOWN(C33,0),-1)) -> 32120 | D56: =IF(MID(ROUNDDOWN(D33,0),LEN(ROUNDDOWN(D33,0)),1)="5",ROUNDDOWN(D33,0),ROUND(ROUNDDOWN(D33,0),-1)) -> 41490 | E56: =IF(MID(ROUNDDOWN(E33,0),LEN(ROUNDDOWN(E33,0)),1)="5",ROUNDDOWN(E33,0),ROUND(ROUNDDOWN(E33,0),-1)) -> 40140 | F56: =IF(MID(ROUNDDOWN(F33,0),LEN(ROUNDDOWN(F33,0)),1)="5",ROUNDDOWN(F33,0),ROUND(ROUNDDOWN(F33,0),-1)) -> 49510 | G56: =+_xlfn.CEILING.MATH(G33,5) -> 0 | H56: =+_xlfn.CEILING.MATH(H33,5) -> 0 | I56: =+_xlfn.CEILING.MATH(I33,5) -> 8025
B57: 10 | C57: =(C56*10)*60% -> 192720 | D57: =(D56*10)*60% -> 248940 | E57: =(E56*10)*60% -> 240840 | F57: =(F56*10)*60% -> 297060 | G57: =+_xlfn.CEILING.MATH(G34,5) -> 0 | H57: =+_xlfn.CEILING.MATH(H34,5) -> 0 | I57: =+_xlfn.CEILING.MATH(I34,5) -> 48130
B58: 20 | C58: =(C56*20)*50% -> 321200 | D58: =(D56*20)*50% -> 414900 | E58: =(E56*20)*50% -> 401400 | F58: =(F56*20)*50% -> 495100 | G58: =+_xlfn.CEILING.MATH(G35,5) -> 0 | H58: =+_xlfn.CEILING.MATH(H35,5) -> 0 | I58: =+_xlfn.CEILING.MATH(I35,5) -> 80220
A59: HU splatky | B59: 10 | C59: =+_xlfn.CEILING.MATH(C36,5) -> 0 | D59: =+_xlfn.CEILING.MATH(D36,5) -> 0 | E59: =+_xlfn.CEILING.MATH(E36,5) -> 0 | F59: =+_xlfn.CEILING.MATH(F36,5) -> 0 | I59: =+_xlfn.CEILING.MATH(I36,5) -> 12040
B60: 20 | C60: =+_xlfn.CEILING.MATH(C37,5) -> 0 | D60: =+_xlfn.CEILING.MATH(D37,5) -> 0 | E60: =+_xlfn.CEILING.MATH(E37,5) -> 0 | F60: =+_xlfn.CEILING.MATH(F37,5) -> 0 | I60: =+_xlfn.CEILING.MATH(I37,5) -> 20065
A61: CZ | B61: 1 | C61: =+_xlfn.CEILING.MATH(C38,1) -> 2237 | D61: =+_xlfn.CEILING.MATH(D38,1) -> 2799 | E61: =+_xlfn.CEILING.MATH(E38,1) -> 3696 | F61: =+_xlfn.CEILING.MATH(F38,1) -> 4256 | G61: =+_xlfn.CEILING.MATH(G38,1) -> 5056 | H61: =+_xlfn.CEILING.MATH(H38,1) -> 0 | I61: =+_xlfn.CEILING.MATH(I38,1) -> 0
B62: 5 | C62: =(C61*5)*90% -> 10066.5 | D62: =(D61*5)*90% -> 12595.5 | E62: =(E61*5)*90% -> 16632 | F62: =(F61*5)*90% -> 19152 | G62: =+_xlfn.CEILING.MATH(G39,1) -> 22746 | H62: =+_xlfn.CEILING.MATH(H39,1) -> 0 | I62: =+_xlfn.CEILING.MATH(I39,1) -> 0
B63: 10 | C63: =(C61*10)*85% -> 19014.5 | D63: =(D61*10)*85% -> 23791.5 | E63: =(E61*10)*85% -> 31416 | F63: =(F61*10)*85% -> 36176 | G63: =+_xlfn.CEILING.MATH(G40,1) -> 42963 | H63: =+_xlfn.CEILING.MATH(H40,1) -> 0 | I63: =+_xlfn.CEILING.MATH(I40,1) -> 0
A64: AT | B64: 1 | C64: =+C41 -> 67.80253 | D64: =+D41 -> 79.294485 | E64: =+E41 -> 90.786439 | F64: =+F41 -> 102.27839 | G64: =+G41 -> 0 | H64: =+H41 -> 0 | I64: =+I41 -> 79.294485
B65: 5 | C65: =+C42 -> 321.77472 | D65: =+D42 -> 376.9361 | E65: =+E42 -> 430.94829 | F65: =+F42 -> 486.10967 | G65: =+G42 -> 0 | H65: =+H42 -> 0 | I65: =+I42 -> 376.9361
B66: 10 | C66: =+C43 -> 610.22277 | D66: =+D43 -> 713.65036 | E66: =+E43 -> 817.07795 | F66: =+F43 -> 920.50554 | G66: =+G43 -> 0 | H66: =+H43 -> 0 | I66: =+I43 -> 713.65036
A67: IT | B67: 1 | C67: =+C44 -> 65.015013 | D67: =+D44 -> 86.686684 | E67: =+E44 -> 86.686684 | F67: =+F44 -> 92.104602 | G67: =+G44 -> 0 | H67: =+H44 -> 0 | I67: =+I44 -> 0
B68: 10 | C68: =+C45 -> 541.79177 | D68: =+D45 -> 639.31429 | E68: =+E45 -> 726.00098 | F68: =+F45 -> 758.50848 | G68: =+G45 -> 0 | H68: =+H45 -> 0 | I68: =+I45 -> 0
B69: 20 | C69: =+C46 -> 975.22519 | D69: =+D46 -> 1083.5835 | E69: =+E46 -> 1191.9419 | F69: =+F46 -> 1300.3003 | G69: =+G46 -> 0 | H69: =+H46 -> 0 | I69: =+I46 -> 0
A72: Prices after inflation rate impact and rounding - EUR - 2026
B73: Years | C73: ST | D73: PR | E73: ST+TK | F73: PR+TK | G73: PL1 | H73: Tkanivo placenty | I73: Tkanivo pupocnika
A74: SK | B74: 1 | C74: =+C50/$K3 -> 83.889623 | D74: =+D50/$K3 -> 96.270461 | E74: =+E50/$K3 -> 106.30036 | F74: =+F50/$K3 -> 118.68119 | G74: =+G50/$K3 -> 204.90994 | H74: =+H50/$K3 -> 0 | I74: =+I50/$K3 -> 22.410733
B75: 10 | C75: =+C51/$K4 -> 713.05589 | D75: =+D51/$K4 -> 818.26938 | E75: =+E51/$K4 -> 903.60028 | F75: =+F51/$K4 -> 1008.802 | G75: =+G51/$K4 -> 1741.7404 | H75: =+H51/$K4 -> 0 | I75: =+I51/$K4 -> 190.53258
B76: 20 | C76: =+C52/$K5 -> 1258.3444 | D76: =+D52/$K5 -> 1443.9978 | E76: =+E52/$K5 -> 1594.5762 | F76: =+F52/$K5 -> 1780.2415 | G76: =+G52/$K5 -> 3073.6492 | H76: =+H52/$K5 -> 0 | I76: =+I52/$K5 -> 336.24369
A77: RO | B77: 1 | C77: =+C53/$K6 -> 77.344122 | D77: =+D53/$K6 -> 105.10868 | E77: =+E53/$K6 -> 105.10868 | F77: =+F53/$K6 -> 132.87323 | G77: =+G53/$K6 -> 224.09964 | H77: =+H53/$K6 -> 91.2264 | I77: =+I53/$K6 -> 27.764557
B78: 10 | C78: =+C54/$K7 -> 657.42504 | D78: =+D54/$K7 -> 893.42377 | E78: =+E54/$K7 -> 893.42377 | F78: =+F54/$K7 -> 1129.4225 | G78: =+G54/$K7 -> 1904.8469 | H78: =+H54/$K7 -> 775.4244 | I78: =+I54/$K7 -> 235.99873
B79: 20 | C79: =+C55/$K8 -> 1160.1618 | D79: =+D55/$K8 -> 1576.6302 | E79: =+E55/$K8 -> 1576.6302 | F79: =+F55/$K8 -> 1993.0985 | G79: =+G55/$K8 -> 3361.4945 | H79: =+H55/$K8 -> 1368.396 | I79: =+I55/$K8 -> 416.46835
A80: HU | B80: 1 | C80: =+C56/$K9 -> 80.75069 | D80: =+D56/$K9 -> 104.30716 | E80: =+E56/$K9 -> 100.91322 | F80: =+F56/$K9 -> 124.4697 | G80: =+G56/$K9 -> 0 | H80: =+H56/$K9 -> 0 | I80: =+I56/$K9 -> 20.175102
B81: 10 | C81: =+C57/$K10 -> 484.50414 | D81: =+D57/$K10 -> 625.84299 | E81: =+E57/$K10 -> 605.47933 | F81: =+F57/$K10 -> 746.81818 | G81: =+G57/$K10 -> 0 | H81: =+H57/$K10 -> 0 | I81: =+I57/$K10 -> 121.00033
B82: 20 | C82: =+C58/$K11 -> 807.5069 | D82: =+D58/$K11 -> 1043.0716 | E82: =+E58/$K11 -> 1009.1322 | F82: =+F58/$K11 -> 1244.697 | G82: =+G58/$K11 -> 0 | H82: =+H58/$K11 -> 0 | I82: =+I58/$K11 -> 201.6756
A83: HU splatky | B83: 10 | C83: =+C59/$K9 -> 0 | D83: =+D59/$K9 -> 0 | E83: =+E59/$K9 -> 0 | F83: =+F59/$K9 -> 0 | G83: =+G59/$K12 -> 0 | H83: =+H59/$K12 -> 0 | I83: =+I59/$K9 -> 30.268939
B84: 20 | C84: =+C60/$K11 -> 0 | D84: =+D60/$K11 -> 0 | E84: =+E60/$K11 -> 0 | F84: =+F60/$K11 -> 0 | G84: =+G60/$K13 -> 0 | H84: =+H60/$K13 -> 0 | I84: =+I60/$K11 -> 50.444041
A85: CZ | B85: 1 | C85: =+C61/$K14 -> 90.61119 | D85: =+D61/$K14 -> 113.37538 | E85: =+E61/$K14 -> 149.70897 | F85: =+F61/$K14 -> 172.39214 | G85: =+G61/$K14 -> 204.79668 | H85: =+H61/$K14 -> 0 | I85: =+I61/$K14 -> 0
B86: 5 | C86: =+C62/$K15 -> 407.75036 | D86: =+D62/$K15 -> 510.1892 | E86: =+E62/$K15 -> 673.69035 | F86: =+F62/$K15 -> 775.76465 | G86: =+G62/$K15 -> 921.34203 | H86: =+H62/$K15 -> 0 | I86: =+I62/$K15 -> 0
B87: 10 | C87: =+C63/$K16 -> 770.19512 | D87: =+D63/$K16 -> 963.69071 | E87: =+E63/$K16 -> 1272.5262 | F87: =+F63/$K16 -> 1465.3332 | G87: =+G63/$K16 -> 1740.2452 | H87: =+H63/$K16 -> 0 | I87: =+I63/$K16 -> 0
A88: AT | B88: 1 | C88: =+C64/$K17 -> 67.80253 | D88: =+D64/$K17 -> 79.294485 | E88: =+E64/$K17 -> 90.786439 | F88: =+F64/$K17 -> 102.27839 | G88: =+G64/$K17 -> 0 | H88: =+H64/$K17 -> 0 | I88: =+I64/$K17 -> 79.294485
B89: 5 | C89: =+C65/$K18 -> 321.77472 | D89: =+D65/$K18 -> 376.9361 | E89: =+E65/$K18 -> 430.94829 | F89: =+F65/$K18 -> 486.10967 | G89: =+G65/$K18 -> 0 | H89: =+H65/$K18 -> 0 | I89: =+I65/$K18 -> 376.9361
B90: 10 | C90: =+C66/$K19 -> 610.22277 | D90: =+D66/$K19 -> 713.65036 | E90: =+E66/$K19 -> 817.07795 | F90: =+F66/$K19 -> 920.50554 | G90: =+G66/$K19 -> 0 | H90: =+H66/$K19 -> 0 | I90: =+I66/$K19 -> 713.65036
A91: IT | B91: 1 | C91: =+C67/$K20 -> 65.015013 | D91: =+D67/$K20 -> 86.686684 | E91: =+E67/$K20 -> 86.686684 | F91: =+F67/$K20 -> 92.104602 | G91: =+G67/$K20 -> 0 | H91: =+H67/$K20 -> 0 | I91: =+I67/$K20 -> 0
B92: 10 | C92: =+C68/$K21 -> 541.79177 | D92: =+D68/$K21 -> 639.31429 | E92: =+E68/$K21 -> 726.00098 | F92: =+F68/$K21 -> 758.50848 | G92: =+G68/$K21 -> 0 | H92: =+H68/$K21 -> 0 | I92: =+I68/$K21 -> 0
B93: 20 | C93: =+C69/$K22 -> 975.22519 | D93: =+D69/$K22 -> 1083.5835 | E93: =+E69/$K22 -> 1191.9419 | F93: =+F69/$K22 -> 1300.3003 | G93: =+G69/$K22 -> 0 | H93: =+H69/$K22 -> 0 | I93: =+I69/$K22 -> 0

Sheet SK
A1: SLOVAKIA
A3: PRICE LIST (from 1.1.2025) | B3: Classic | C3: Premium | D3: Cl.+Tissue | E3: PR.+Tissue | F3: Placenta | J3: CB* | K3: pupocnikova krv
B4: =+'COLLECTION PRICE'!C25 -> 1400 | C4: =+'COLLECTION PRICE'!D25 -> 1600 | D4: =+'COLLECTION PRICE'!E25 -> 1800 | E4: =+'COLLECTION PRICE'!F25 -> 2100 | F4: =+'COLLECTION PRICE'!G25 -> 2500 | G4: Collection | J4: PB* | K4: placentarna krv
B5: =+'STORAGE PRICE'!C74 -> 83.889623 | C5: =+'STORAGE PRICE'!D74 -> 96.270461 | D5: =+'STORAGE PRICE'!E74 -> 106.30036 | E5: =+'STORAGE PRICE'!F74 -> 118.68119 | F5: =+'STORAGE PRICE'!G74 -> 204.90994 | G5: 1 Year storage | J5: T (CB) | K5: tkanivo pupocnika
B6: =+'STORAGE PRICE'!C75 -> 713.05589 | C6: =+'STORAGE PRICE'!D75 -> 818.26938 | D6: =+'STORAGE PRICE'!E75 -> 903.60028 | E6: =+'STORAGE PRICE'!F75 -> 1008.802 | F6: =+'STORAGE PRICE'!G75 -> 1741.7404 | G6: 10 Years storage | J6: T (PB) | K6: tkanivo pupocnika
B7: =+'STORAGE PRICE'!C76 -> 1258.3444 | C7: =+'STORAGE PRICE'!D76 -> 1443.9978 | D7: =+'STORAGE PRICE'!E76 -> 1594.5762 | E7: =+'STORAGE PRICE'!F76 -> 1780.2415 | F7: =+'STORAGE PRICE'!G76 -> 3073.6492 | G7: 20 Years storage | J7: PL | K7: tkanivo placenty
A9: Failed Collection or Contamination
A10: Product | B10: CB* | C10: PB* | D10: T (CB) | E10: T (PB) | F10: PL | H10: Discounted
A11: Price - collection | B11: =+B4-H13 -> 900 | C11: =+C4-B4 -> 200 | D11: =+D4-B4 -> 400 | E11: =+E4-C4 -> 500 | F11: =+F4-E4 -> 400 | G11: Product | H11: price | J11: 15% discount | K11: 25% discount
A12: Price - storage | B12: =+B5 -> 83.889623 | C12: =+C5-B5 -> 12.380837 | D12: =+D5-B12 -> 22.410733 | E12: =+E5-C5 -> 22.410733 | F12: =+F5-E5 -> 86.228751 | G12: adjustment | H12: COLLECTION | I12: 1 YEAR STORAGE | J12: 10 YEAR STORAGE | K12: 20 YEAR STORAGE
A13: FLAAT FEE | B13: FALSE | C13: FALSE | D13: FALSE | E13: FALSE | F13: FALSE | G13: ALL | H13: 500 | L13: Cena za samostatne tkanivo popocnika kym nedojde k zmenev zmluve
A14: Classic | B14: TRUE | C14: FALSE | D14: FALSE | E14: FALSE | F14: FALSE | G14: Classic | H14: =+B4 -> 1400 | I14: =+B5 -> 83.889623 | J14: =+B6 -> 713.05589 | K14: =+B7 -> 1258.3444
A15: Premium | B15: TRUE | C15: TRUE | D15: FALSE | E15: FALSE | F15: FALSE | G15: Premium | H15: =+C4 -> 1600 | I15: =+C5 -> 96.270461 | J15: =+C6 -> 818.26938 | K15: =+C7 -> 1443.9978
A16: Premium | B16: TRUE | C16: FALSE | D16: FALSE | E16: FALSE | F16: FALSE | G16: CB | H16: =+$B$11+H13 -> 1400 | I16: =+$B$12 -> 83.889623 | J16: =+I16*10*(100%-15%) -> 713.0618 | K16: =+I16*20*(100%-25%) -> 1258.3444
A17: Premium | B17: FALSE | C17: TRUE | D17: FALSE | E17: FALSE | F17: FALSE | G17: PB | H17: =+$C$11+H13 -> 700 | I17: =+$C$12 -> 12.380837 | J17: =+I17*10*(100%-15%) -> 105.23712 | K17: =+I17*20*(100%-25%) -> 185.71256
A18: Classic+Tissue | B18: TRUE | C18: FALSE | D18: TRUE | E18: FALSE | F18: FALSE | G18: Classic+Tissue | H18: =+D4 -> 1800 | I18: =+D5 -> 106.30036 | J18: =+D6 -> 903.60028 | K18: =+D7 -> 1594.5762
A19: Classic+Tissue | B19: TRUE | C19: FALSE | D19: FALSE | E19: FALSE | F19: FALSE | G19: CB | H19: =+$B$11+H13 -> 1400 | I19: =+$B$12 -> 83.889623 | J19: =+I19*10*(100%-15%) -> 713.0618 | K19: =+I19*20*(100%-25%) -> 1258.3444
A20: Classic+Tissue | B20: FALSE | C20: FALSE | D20: TRUE | E20: FALSE | F20: FALSE | G20: T (CB) | H20: =+$D$11+H13 -> 900 | I20: =+$D$12 -> 22.410733 | J20: =+I20*10*(100%-15%) -> 190.49123 | K20: =+I20*20*(100%-25%) -> 336.161 | L20: v zmluve je aktualne uvedena cena za odber samostatneho tkaniva 1200 EUR
A21: Premium+Tissue | B21: TRUE | C21: TRUE | D21: FALSE | E21: TRUE | F21: FALSE | G21: Premium+Tissue | H21: =+E4 -> 2100 | I21: =+E5 -> 118.68119 | J21: =+E6 -> 1008.802 | K21: =+E7 -> 1780.2415
A22: Premium+Tissue | B22: TRUE | C22: FALSE | D22: FALSE | E22: FALSE | F22: FALSE | G22: CB | H22: =+$B$11+H13 -> 1400 | I22: =+$B$12 -> 83.889623 | J22: =+I22*10*(100%-15%) -> 713.0618 | K22: =+I22*20*(100%-25%) -> 1258.3444
A23: Premium+Tissue | B23: TRUE | C23: TRUE | D23: FALSE | E23: FALSE | F23: FALSE | G23: CB + PB | H23: =+$B$11+$C$11+H13 -> 1600 | I23: =+$B$12+$C$12 -> 96.270461 | J23: =+I23*10*(100%-15%) -> 818.29892 | K23: =+I23*20*(100%-25%) -> 1444.0569
A24: Premium+Tissue | B24: TRUE | C24: FALSE | D24: TRUE | E24: FALSE | F24: FALSE | G24: CB + T (CB) | H24: =+$B$11+$D$11+H13 -> 1800 | I24: =+$B$12+$D$12 -> 106.30036 | J24: =+I24*10*(100%-15%) -> 903.55303 | K24: =+I24*20*(100%-25%) -> 1594.5053
A25: Premium+Tissue | B25: FALSE | C25: TRUE | D25: FALSE | E25: FALSE | F25: FALSE | G25: PB | H25: =+$C$11+H13 -> 700 | I25: =+$C$12 -> 12.380837 | J25: =+I25*10*(100%-15%) -> 105.23712 | K25: =+I25*20*(100%-25%) -> 185.71256
A26: Premium+Tissue | B26: FALSE | C26: TRUE | D26: FALSE | E26: TRUE | F26: FALSE | G26: PB+T (PB) | H26: =+$C$11+$E$11+H13 -> 1200 | I26: =+$C$12+$E$12 -> 34.79157 | J26: =+I26*10*(100%-15%) -> 295.72835 | K26: =+I26*20*(100%-25%) -> 521.87355
A27: Premium+Tissue | B27: FALSE | C27: FALSE | D27: FALSE | E27: TRUE | F27: FALSE | G27: T (PB) | H27: =+$E$11+H13 -> 1000 | I27: =+$E$12 -> 22.410733 | J27: =+I27*10*(100%-15%) -> 190.49123 | K27: =+I27*20*(100%-25%) -> 336.161 | L27: v zmluve je aktualne uvedena cena za odber samostatneho tkaniva 1200 EUR
A28: PLACENTA | B28: TRUE | C28: TRUE | D28: FALSE | E28: TRUE | F28: TRUE | G28: Placenta | H28: =+F4 -> 2500 | I28: =+F5 -> 204.90994 | J28: =+F6 -> 1741.7404 | K28: =+F7 -> 3073.6492
A29: PLACENTA | B29: TRUE | C29: FALSE | D29: FALSE | E29: FALSE | F29: FALSE | G29: CB | H29: =+$B$11+H13 -> 1400 | I29: =+$B$12 -> 83.889623 | J29: =+I29*10*(100%-15%) -> 713.0618 | K29: =+I29*20*(100%-25%) -> 1258.3444
A30: PLACENTA | B30: TRUE | C30: TRUE | D30: FALSE | E30: FALSE | F30: FALSE | G30: CB + PB | H30: =+$B$11+$C$11+H13 -> 1600 | I30: =+$B$12+$C$12 -> 96.270461 | J30: =+I30*10*(100%-15%) -> 818.29892 | K30: =+I30*20*(100%-25%) -> 1444.0569
A31: PLACENTA | B31: TRUE | C31: TRUE | D31: FALSE | E31: TRUE | F31: FALSE | G31: CB + PB + T (PB) | H31: =+$B$11+$C$11+$E$11+H13 -> 2100 | I31: =+$B$12+$C$12+$E$12 -> 118.68119 | J31: =+I31*10*(100%-15%) -> 1008.7901 | K31: =+I31*20*(100%-25%) -> 1780.2179
A32: PLACENTA | B32: TRUE | C32: FALSE | D32: TRUE | E32: FALSE | F32: FALSE | G32: CB + T (CB) | H32: =+$B$11+$D$11+H13 -> 1800 | I32: =+$B$12+$D$12 -> 106.30036 | J32: =+I32*10*(100%-15%) -> 903.55303 | K32: =+I32*20*(100%-25%) -> 1594.5053
A33: PLACENTA | B33: FALSE | C33: TRUE | D33: FALSE | E33: FALSE | F33: FALSE | G33: PB | H33: =+$C$11+H13 -> 700 | I33: =+$C$12 -> 12.380837 | J33: =+I33*10*(100%-15%) -> 105.23712 | K33: =+I33*20*(100%-25%) -> 185.71256
A34: PLACENTA | B34: FALSE | C34: TRUE | D34: FALSE | E34: TRUE | F34: FALSE | G34: PB+T (PB) | H34: =+$C$11+$E$11+H13 -> 1200 | I34: =+$C$12+$E$12 -> 34.79157 | J34: =+I34*10*(100%-15%) -> 295.72835 | K34: =+I34*20*(100%-25%) -> 521.87355
A35: PLACENTA | B35: FALSE | C35: FALSE | D35: FALSE | E35: TRUE | F35: FALSE | G35: T (PB) | H35: =+$E$11+H13 -> 1000 | I35: =+$E$12 -> 22.410733 | J35: =+I35*10*(100%-15%) -> 190.49123 | K35: =+I35*20*(100%-25%) -> 336.161 | L35: v zmluve je aktualne uvedena cena za odber samostatneho tkaniva 1200 EUR
A36: PLACENTA | B36: FALSE | C36: FALSE | D36: FALSE | E36: FALSE | F36: TRUE | G36: PL | H36: =+$F$11+H13 -> 900 | I36: =+$F$12 -> 86.228751 | J36: =+I36*10*(100%-15%) -> 732.94438 | K36: =+I36*20*(100%-25%) -> 1293.4313
A37: PLACENTA | B37: TRUE | C37: FALSE | D37: FALSE | E37: FALSE | F37: TRUE | G37: CB+PL | H37: =+$B$11+$F$11+H13 -> 1800 | I37: =+$B$12+$F$12 -> 170.11837 | J37: =+I37*10*(100%-15%) -> 1446.0062 | K37: =+I37*20*(100%-25%) -> 2551.7756
A38: PLACENTA | B38: TRUE | C38: TRUE | D38: FALSE | E38: FALSE | F38: TRUE | G38: CB+PB+PL | H38: =+$B$11+$C$11+$F$11+H13 -> 2000 | I38: =+$B$12+$C$12+$F$12 -> 182.49921 | J38: =+I38*10*(100%-15%) -> 1551.2433 | K38: =+I38*20*(100%-25%) -> 2737.4882
A39: PLACENTA | B39: TRUE | C39: FALSE | D39: FALSE | E39: TRUE | F39: TRUE | G39: CB+T(PB)+PL | H39: =+$B$11+$E$11+$F$11+H13 -> 2300 | I39: =+$B$12+$E$12+$F$12 -> 192.52911 | J39: =+I39*10*(100%-15%) -> 1636.4974 | K39: =+I39*20*(100%-25%) -> 2887.9366
A40: PLACENTA | B40: FALSE | C40: TRUE | D40: FALSE | E40: FALSE | F40: TRUE | G40: PB+PL | H40: =+$C$11+$F$11+H13 -> 1100 | I40: =+$C$12+$F$12 -> 98.609588 | J40: =+I40*10*(100%-15%) -> 838.1815 | K40: =+I40*20*(100%-25%) -> 1479.1438
A41: PLACENTA | B41: FALSE | C41: TRUE | D41: FALSE | E41: TRUE | F41: TRUE | G41: PB+T(PB)+PL | H41: =+$C$11+$E$11+$F$11+H13 -> 1600 | I41: =+$C$12+$E$12+$F$12 -> 121.02032 | J41: =+I41*10*(100%-15%) -> 1028.6727 | K41: =+I41*20*(100%-25%) -> 1815.3048
A42: PLACENTA | B42: FALSE | C42: FALSE | D42: FALSE | E42: TRUE | F42: TRUE | G42: T(PB)+PL | H42: =+$E$11+$F$11+H13 -> 1400 | I42: =+$E$12+$F$12 -> 108.63948 | J42: =+I42*10*(100%-15%) -> 923.43561 | K42: =+I42*20*(100%-25%) -> 1629.5923
A43: * collection of blood (CB+PB) <20ml = discount 400 EUR
A44: ** CONTAMINATION = discount 100% from collection fee for contaminated item
A45: *** storage fee depend on REAL stored product (independent from volume or contamination)

Sheet CZ
A1: CZECHIA
A3: PRICE LIST (from 1.1.2025) | B3: Classic | C3: Premium | D3: Cl.+Tissue | E3: PR.+Tissue | F3: Placenta | J3: CB* | K3: pupocnikova krv
B4: =+'COLLECTION PRICE'!C34 -> 35000 | C4: =+'COLLECTION PRICE'!D34 -> 40000 | D4: =+'COLLECTION PRICE'!E34 -> 45000 | E4: =+'COLLECTION PRICE'!F34 -> 52500 | F4: =+'COLLECTION PRICE'!G34 -> 62500 | G4: Collection | J4: PB | K4: placentarna krv
B5: =+'STORAGE PRICE'!C61 -> 2237 | C5: =+'STORAGE PRICE'!D61 -> 2799 | D5: =+'STORAGE PRICE'!E61 -> 3696 | E5: =+'STORAGE PRICE'!F61 -> 4256 | F5: =+'STORAGE PRICE'!G61 -> 5056 | G5: 1 Year storage | J5: T (CB) | K5: tkanivo pupocnika
B6: =+'STORAGE PRICE'!C62 -> 10066.5 | C6: =+'STORAGE PRICE'!D62 -> 12595.5 | D6: =+'STORAGE PRICE'!E62 -> 16632 | E6: =+'STORAGE PRICE'!F62 -> 19152 | F6: =+'STORAGE PRICE'!G62 -> 22746 | G6: 5 Years storage | J6: T (PB) | K6: tkanivo pupocnika
B7: =+'STORAGE PRICE'!C63 -> 19014.5 | C7: =+'STORAGE PRICE'!D63 -> 23791.5 | D7: =+'STORAGE PRICE'!E63 -> 31416 | E7: =+'STORAGE PRICE'!F63 -> 36176 | F7: =+'STORAGE PRICE'!G63 -> 42963 | G7: 10 Years storage | J7: PL | K7: tkanivo placenty
A9: Failed Collection or Contamination
A10: Product | B10: CB* | C10: PB | D10: T (CB) | E10: T (PB) | F10: PL | H10: Discounted
A11: Price - collection | B11: =+B4-H13 -> 22500 | C11: =+C4-B4 -> 5000 | D11: =+D4-B4 -> 10000 | E11: =+E4-C4 -> 12500 | F11: =+F4-E4 -> 10000 | G11: Product | H11: price | J11: 10% discount | K11: 15% discount | M11: Collection
A12: Price - storage | B12: =+B5 -> 2237 | C12: =+C5-B5 -> 562 | D12: =+D5-B12 -> 1459 | E12: =+E5-C5 -> 1457 | F12: =+F5-E5 -> 800 | G12: adjustment | H12: COLLECTION | I12: 1 YEAR STORAGE | J12: 5 YEAR STORAGE | K12: 10 YEAR STORAGE | M12: in EUR
A13: FLAAT FEE | B13: FALSE | C13: FALSE | D13: FALSE | E13: FALSE | F13: FALSE | G13: ALL | H13: =500*25 -> 12500 | M13: =+H13/25 -> 500
A14: Classic | B14: TRUE | C14: FALSE | D14: FALSE | E14: FALSE | F14: FALSE | G14: Classic | H14: =+B4 -> 35000 | I14: =+B5 -> 2237 | J14: =+B6 -> 10066.5 | K14: =+B7 -> 19014.5 | M14: =+H14/25 -> 1400
A15: Premium | B15: TRUE | C15: TRUE | D15: FALSE | E15: FALSE | F15: FALSE | G15: Premium | H15: =+C4 -> 40000 | I15: =+C5 -> 2799 | J15: =+C6 -> 12595.5 | K15: =+C7 -> 23791.5 | M15: =+H15/25 -> 1600
A16: Premium | B16: TRUE | C16: FALSE | D16: FALSE | E16: FALSE | F16: FALSE | G16: CB | H16: =+$B$11+H13 -> 35000 | I16: =+$B$12 -> 2237 | J16: =+I16*5*(100%-10%) -> 10066.5 | K16: =+I16*10*(100%-15%) -> 19014.5 | M16: =+H16/25 -> 1400
A17: Premium | B17: FALSE | C17: TRUE | D17: FALSE | E17: FALSE | F17: FALSE | G17: PB | H17: =+$C$11+H13 -> 17500 | I17: =+$C$12 -> 562 | J17: =+I17*5*(100%-10%) -> 2529 | K17: =+I17*10*(100%-15%) -> 4777 | M17: =+H17/25 -> 700
A18: Classic+Tissue | B18: TRUE | C18: FALSE | D18: TRUE | E18: FALSE | F18: FALSE | G18: Classic+Tissue | H18: =+D4 -> 45000 | I18: =+D5 -> 3696 | J18: =+D6 -> 16632 | K18: =+D7 -> 31416 | M18: =+H18/25 -> 1800
A19: Classic+Tissue | B19: TRUE | C19: FALSE | D19: FALSE | E19: FALSE | F19: FALSE | G19: CB | H19: =+$B$11+H13 -> 35000 | I19: =+$B$12 -> 2237 | J19: =+I19*5*(100%-10%) -> 10066.5 | K19: =+I19*10*(100%-15%) -> 19014.5 | M19: =+H19/25 -> 1400
A20: Classic+Tissue | B20: FALSE | C20: FALSE | D20: TRUE | E20: FALSE | F20: FALSE | G20: T (CB) | H20: =+$D$11+H13 -> 22500 | I20: =+$D$12 -> 1459 | J20: =+I20*5*(100%-10%) -> 6565.5 | K20: =+I20*10*(100%-15%) -> 12401.5 | M20: =+H20/25 -> 900
A21: Premium+Tissue | B21: TRUE | C21: TRUE | D21: FALSE | E21: TRUE | F21: FALSE | G21: Premium+Tissue | H21: =+E4 -> 52500 | I21: =+E5 -> 4256 | J21: =+E6 -> 19152 | K21: =+E7 -> 36176 | M21: =+H21/25 -> 2100
A22: Premium+Tissue | B22: TRUE | C22: FALSE | D22: FALSE | E22: FALSE | F22: FALSE | G22: CB | H22: =+$B$11+H13 -> 35000 | I22: =+$B$12 -> 2237 | J22: =+I22*5*(100%-10%) -> 10066.5 | K22: =+I22*10*(100%-15%) -> 19014.5 | M22: =+H22/25 -> 1400
A23: Premium+Tissue | B23: TRUE | C23: TRUE | D23: FALSE | E23: FALSE | F23: FALSE | G23: CB + PB | H23: =+$B$11+$C$11+H13 -> 40000 | I23: =+$B$12+$C$12 -> 2799 | J23: =+I23*5*(100%-10%) -> 12595.5 | K23: =+I23*10*(100%-15%) -> 23791.5 | M23: =+H23/25 -> 1600
A24: Premium+Tissue | B24: TRUE | C24: FALSE | D24: TRUE | E24: FALSE | F24: FALSE | G24: CB + T (CB) | H24: =+$B$11+$D$11+H13 -> 45000 | I24: =+$B$12+$D$12 -> 3696 | J24: =+I24*5*(100%-10%) -> 16632 | K24: =+I24*10*(100%-15%) -> 31416 | M24: =+H24/25 -> 1800
A25: Premium+Tissue | B25: FALSE | C25: TRUE | D25: FALSE | E25: FALSE | F25: FALSE | G25: PB | H25: =+$C$11+H13 -> 17500 | I25: =+$C$12 -> 562 | J25: =+I25*5*(100%-10%) -> 2529 | K25: =+I25*10*(100%-15%) -> 4777 | M25: =+H25/25 -> 700
A26: Premium+Tissue | B26: FALSE | C26: TRUE | D26: FALSE | E26: TRUE | F26: FALSE | G26: PB+T (PB) | H26: =+$C$11+$E$11+H13 -> 30000 | I26: =+$C$12+$E$12 -> 2019 | J26: =+I26*5*(100%-10%) -> 9085.5 | K26: =+I26*10*(100%-15%) -> 17161.5 | M26: =+H26/25 -> 1200
A27: Premium+Tissue | B27: FALSE | C27: FALSE | D27: FALSE | E27: TRUE | F27: FALSE | G27: T (PB) | H27: =+$E$11+H13 -> 25000 | I27: =+$E$12 -> 1457 | J27: =+I27*5*(100%-10%) -> 6556.5 | K27: =+I27*10*(100%-15%) -> 12384.5 | M27: =+H27/25 -> 1000
A28: PLACENTA | B28: TRUE | C28: TRUE | D28: FALSE | E28: TRUE | F28: TRUE | G28: Placenta | H28: =+F4 -> 62500 | I28: =+F5 -> 5056 | J28: =+F6 -> 22746 | K28: =+F7 -> 42963 | M28: =+H28/25 -> 2500
A29: PLACENTA | B29: TRUE | C29: FALSE | D29: FALSE | E29: FALSE | F29: FALSE | G29: CB | H29: =+$B$11+H13 -> 35000 | I29: =+$B$12 -> 2237 | J29: =+I29*5*(100%-10%) -> 10066.5 | K29: =+I29*10*(100%-15%) -> 19014.5 | M29: =+H29/25 -> 1400
A30: PLACENTA | B30: TRUE | C30: TRUE | D30: FALSE | E30: FALSE | F30: FALSE | G30: CB + PB | H30: =+$B$11+$C$11+H13 -> 40000 | I30: =+$B$12+$C$12 -> 2799 | J30: =+I30*5*(100%-10%) -> 12595.5 | K30: =+I30*10*(100%-15%) -> 23791.5 | M30: =+H30/25 -> 1600
A31: PLACENTA | B31: TRUE | C31: TRUE | D31: FALSE | E31: TRUE | F31: FALSE | G31: CB + PB + T (PB) | H31: =+$B$11+$C$11+$E$11+H13 -> 52500 | I31: =+$B$12+$C$12+$E$12 -> 4256 | J31: =+I31*5*(100%-10%) -> 19152 | K31: =+I31*10*(100%-15%) -> 36176 | M31: =+H31/25 -> 2100
A32: PLACENTA | B32: TRUE | C32: FALSE | D32: TRUE | E32: FALSE | F32: FALSE | G32: CB + T (CB) | H32: =+$B$11+$D$11+H13 -> 45000 | I32: =+$B$12+$D$12 -> 3696 | J32: =+I32*5*(100%-10%) -> 16632 | K32: =+I32*10*(100%-15%) -> 31416 | M32: =+H32/25 -> 1800
A33: PLACENTA | B33: FALSE | C33: TRUE | D33: FALSE | E33: FALSE | F33: FALSE | G33: PB | H33: =+$C$11+H13 -> 17500 | I33: =+$C$12 -> 562 | J33: =+I33*5*(100%-10%) -> 2529 | K33: =+I33*10*(100%-15%) -> 4777 | M33: =+H33/25 -> 700
A34: PLACENTA | B34: FALSE | C34: TRUE | D34: FALSE | E34: TRUE | F34: FALSE | G34: PB+T (PB) | H34: =+$C$11+$E$11+H13 -> 30000 | I34: =+$C$12+$E$12 -> 2019 | J34: =+I34*5*(100%-10%) -> 9085.5 | K34: =+I34*10*(100%-15%) -> 17161.5 | M34: =+H34/25 -> 1200
A35: PLACENTA | B35: FALSE | C35: FALSE | D35: FALSE | E35: TRUE | F35: FALSE | G35: T (PB) | H35: =+$E$11+H13 -> 25000 | I35: =+$E$12 -> 1457 | J35: =+I35*5*(100%-10%) -> 6556.5 | K35: =+I35*10*(100%-15%) -> 12384.5 | M35: =+H35/25 -> 1000
A36: PLACENTA | B36: FALSE | C36: FALSE | D36: FALSE | E36: FALSE | F36: TRUE | G36: PL | H36: =+$F$11+H13 -> 22500 | I36: =+$F$12 -> 800 | J36: =+I36*5*(100%-10%) -> 3600 | K36: =+I36*10*(100%-15%) -> 6800 | M36: =+H36/25 -> 900
A37: PLACENTA | B37: TRUE | C37: FALSE | D37: FALSE | E37: FALSE | F37: TRUE | G37: CB+PL | H37: =+$B$11+$F$11+H13 -> 45000 | I37: =+$B$12+$F$12 -> 3037 | J37: =+I37*5*(100%-10%) -> 13666.5 | K37: =+I37*10*(100%-15%) -> 25814.5 | M37: =+H37/25 -> 1800
A38: PLACENTA | B38: TRUE | C38: TRUE | D38: FALSE | E38: FALSE | F38: TRUE | G38: CB+PB+PL | H38: =+$B$11+$C$11+$F$11+H13 -> 50000 | I38: =+$B$12+$C$12+$F$12 -> 3599 | J38: =+I38*5*(100%-10%) -> 16195.5 | K38: =+I38*10*(100%-15%) -> 30591.5 | M38: =+H38/25 -> 2000
A39: PLACENTA | B39: TRUE | C39: FALSE | D39: FALSE | E39: TRUE | F39: TRUE | G39: CB+T(PB)+PL | H39: =+$B$11+$E$11+$F$11+H13 -> 57500 | I39: =+$B$12+$E$12+$F$12 -> 4494 | J39: =+I39*5*(100%-10%) -> 20223 | K39: =+I39*10*(100%-15%) -> 38199 | M39: =+H39/25 -> 2300
A40: PLACENTA | B40: FALSE | C40: TRUE | D40: FALSE | E40: FALSE | F40: TRUE | G40: PB+PL | H40: =+$C$11+$F$11+H13 -> 27500 | I40: =+$C$12+$F$12 -> 1362 | J40: =+I40*5*(100%-10%) -> 6129 | K40: =+I40*10*(100%-15%) -> 11577 | M40: =+H40/25 -> 1100
A41: PLACENTA | B41: FALSE | C41: TRUE | D41: FALSE | E41: TRUE | F41: TRUE | G41: PB+T(PB)+PL | H41: =+$C$11+$E$11+$F$11+H13 -> 40000 | I41: =+$C$12+$E$12+$F$12 -> 2819 | J41: =+I41*5*(100%-10%) -> 12685.5 | K41: =+I41*10*(100%-15%) -> 23961.5 | M41: =+H41/25 -> 1600
A42: PLACENTA | B42: FALSE | C42: FALSE | D42: FALSE | E42: TRUE | F42: TRUE | G42: T(PB)+PL | H42: =+$E$11+$F$11+H13 -> 35000 | I42: =+$E$12+$F$12 -> 2257 | J42: =+I42*5*(100%-10%) -> 10156.5 | K42: =+I42*10*(100%-15%) -> 19184.5 | M42: =+H42/25 -> 1400
A43: * collection of blood (CB+PB) <20ml = discount 10 000 CZK
A44: ** CONTAMINATION = discount 100% from collection fee for contaminated item
A45: *** storage fee depend on REAL stored product (independent from volume or contamination)

Sheet RO
A1: ROMANIA
A3: PRICE LIST (from 1.1.2025) | B3: Classic | C3: Premium | D3: Cl.+Tissue | E3: PR.+Tissue | F3: Placenta | J3: CB* | K3: cord blood
B4: =+'COLLECTION PRICE'!C28 -> 7000 | C4: =+'COLLECTION PRICE'!D28 -> 8000 | D4: =+'COLLECTION PRICE'!E28 -> 9000 | E4: =+'COLLECTION PRICE'!F28 -> 10500 | F4: =+'COLLECTION PRICE'!G28 -> 12500 | G4: Collection | J4: PB | K4: placental blood
B5: =+'STORAGE PRICE'!C53 -> 390 | C5: =+'STORAGE PRICE'!D53 -> 530 | D5: =+'STORAGE PRICE'!E53 -> 530 | E5: =+'STORAGE PRICE'!F53 -> 670 | F5: =+'STORAGE PRICE'!G53 -> 1130 | G5: 1 Year storage | J5: T (CB) | K5: cord tissue
B6: =+'STORAGE PRICE'!C54 -> 3315 | C6: =+'STORAGE PRICE'!D54 -> 4505 | D6: =+'STORAGE PRICE'!E54 -> 4505 | E6: =+'STORAGE PRICE'!F54 -> 5695 | F6: =+'STORAGE PRICE'!G54 -> 9605 | G6: 10 Years storage | J6: T (PB) | K6: cord tissue
B7: =+'STORAGE PRICE'!C55 -> 5850 | C7: =+'STORAGE PRICE'!D55 -> 7950 | D7: =+'STORAGE PRICE'!E55 -> 7950 | E7: =+'STORAGE PRICE'!F55 -> 10050 | F7: =+'STORAGE PRICE'!G55 -> 16950 | G7: 20 Years storage | J7: PL | K7: placenta
A9: Failed Collection or Contamination
A10: Product | B10: CB* | C10: PB | D10: T (CB) | E10: T (PB) | F10: PL | H10: Discounted
A11: Price - collection | B11: =+B4-H13 -> 4500 | C11: =+C4-B4 -> 1000 | D11: =+D4-B4 -> 2000 | E11: =+E4-C4 -> 2500 | F11: =+F4-E4 -> 2000 | G11: Product | H11: price | J11: 15% discount | K11: 25% discount | M11: Collection
A12: Price - storage | B12: =+B5 -> 390 | C12: =+C5-B5 -> 140 | D12: =+D5-B12 -> 140 | E12: =+E5-C5 -> 140 | F12: =+F5-E5 -> 460 | G12: adjustment | H12: COLLECTION | I12: 1 YEAR STORAGE | J12: 10 YEAR STORAGE | K12: 20 YEAR STORAGE | M12: in EUR
A13: FLAAT FEE | B13: FALSE | C13: FALSE | D13: FALSE | E13: FALSE | F13: FALSE | G13: ALL | H13: 2500 | L13: Price for Tissue and Placenta ONLY till contract will be changed | M13: =+H13/5 -> 500
A14: Classic | B14: TRUE | C14: FALSE | D14: FALSE | E14: FALSE | F14: FALSE | G14: Classic | H14: =+B4 -> 7000 | I14: =+B5 -> 390 | J14: =+B6 -> 3315 | K14: =+B7 -> 5850 | M14: =+H14/5 -> 1400
A15: Premium | B15: TRUE | C15: TRUE | D15: FALSE | E15: FALSE | F15: FALSE | G15: Premium | H15: =+C4 -> 8000 | I15: =+C5 -> 530 | J15: =+C6 -> 4505 | K15: =+C7 -> 7950 | M15: =+H15/5 -> 1600
A16: Premium | B16: TRUE | C16: FALSE | D16: FALSE | E16: FALSE | F16: FALSE | G16: CB | H16: =+$B$11+H13 -> 7000 | I16: =+$B$12 -> 390 | J16: =+I16*10*(100%-15%) -> 3315 | K16: =+I16*20*(100%-25%) -> 5850 | M16: =+H16/5 -> 1400
A17: Premium | B17: FALSE | C17: TRUE | D17: FALSE | E17: FALSE | F17: FALSE | G17: PB | H17: =+$C$11+H13 -> 3500 | I17: =+$C$12 -> 140 | J17: =+I17*10*(100%-15%) -> 1190 | K17: =+I17*20*(100%-25%) -> 2100 | M17: =+H17/5 -> 700
A18: Classic+Tissue | B18: TRUE | C18: FALSE | D18: TRUE | E18: FALSE | F18: FALSE | G18: Classic+Tissue | H18: =+D4 -> 9000 | I18: =+D5 -> 530 | J18: =+D6 -> 4505 | K18: =+D7 -> 7950 | M18: =+H18/5 -> 1800
A19: Classic+Tissue | B19: TRUE | C19: FALSE | D19: FALSE | E19: FALSE | F19: FALSE | G19: CB | H19: =+$B$11+H13 -> 7000 | I19: =+$B$12 -> 390 | J19: =+I19*10*(100%-15%) -> 3315 | K19: =+I19*20*(100%-25%) -> 5850 | M19: =+H19/5 -> 1400
A20: Classic+Tissue | B20: FALSE | C20: FALSE | D20: TRUE | E20: FALSE | F20: FALSE | G20: T (CB) | H20: =+$D$11+H13 -> 4500 | I20: =+$D$12 -> 140 | J20: =+I20*10*(100%-15%) -> 1190 | K20: =+I20*20*(100%-25%) -> 2100 | L20: price for collection is written in contract in value 3 000 RON | M20: =+H20/5 -> 900
A21: Premium+Tissue | B21: TRUE | C21: TRUE | D21: FALSE | E21: TRUE | F21: FALSE | G21: Premium+Tissue | H21: =+E4 -> 10500 | I21: =+E5 -> 670 | J21: =+E6 -> 5695 | K21: =+E7 -> 10050 | M21: =+H21/5 -> 2100
A22: Premium+Tissue | B22: TRUE | C22: FALSE | D22: FALSE | E22: FALSE | F22: FALSE | G22: CB | H22: =+$B$11+H13 -> 7000 | I22: =+$B$12 -> 390 | J22: =+I22*10*(100%-15%) -> 3315 | K22: =+I22*20*(100%-25%) -> 5850 | M22: =+H22/5 -> 1400
A23: Premium+Tissue | B23: TRUE | C23: TRUE | D23: FALSE | E23: FALSE | F23: FALSE | G23: CB + PB | H23: =+$B$11+$C$11+H13 -> 8000 | I23: =+$B$12+$C$12 -> 530 | J23: =+I23*10*(100%-15%) -> 4505 | K23: =+I23*20*(100%-25%) -> 7950 | M23: =+H23/5 -> 1600
A24: Premium+Tissue | B24: TRUE | C24: FALSE | D24: TRUE | E24: FALSE | F24: FALSE | G24: CB + T (CB) | H24: =+$B$11+$D$11+H13 -> 9000 | I24: =+$B$12+$D$12 -> 530 | J24: =+I24*10*(100%-15%) -> 4505 | K24: =+I24*20*(100%-25%) -> 7950 | M24: =+H24/5 -> 1800
A25: Premium+Tissue | B25: FALSE | C25: TRUE | D25: FALSE | E25: FALSE | F25: FALSE | G25: PB | H25: =+$C$11+H13 -> 3500 | I25: =+$C$12 -> 140 | J25: =+I25*10*(100%-15%) -> 1190 | K25: =+I25*20*(100%-25%) -> 2100 | M25: =+H25/5 -> 700
A26: Premium+Tissue | B26: FALSE | C26: TRUE | D26: FALSE | E26: TRUE | F26: FALSE | G26: PB+T (PB) | H26: =+$C$11+$E$11+H13 -> 6000 | I26: =+$C$12+$E$12 -> 280 | J26: =+I26*10*(100%-15%) -> 2380 | K26: =+I26*20*(100%-25%) -> 4200 | M26: =+H26/5 -> 1200
A27: Premium+Tissue | B27: FALSE | C27: FALSE | D27: FALSE | E27: TRUE | F27: FALSE | G27: T (PB) | H27: =+$E$11+H13 -> 5000 | I27: =+$E$12 -> 140 | J27: =+I27*10*(100%-15%) -> 1190 | K27: =+I27*20*(100%-25%) -> 2100 | L27: price for collection is written in contract in value 3 000 RON | M27: =+H27/5 -> 1000
A28: PLACENTA | B28: TRUE | C28: TRUE | D28: FALSE | E28: TRUE | F28: TRUE | G28: Placenta | H28: =+F4 -> 12500 | I28: =+F5 -> 1130 | J28: =+F6 -> 9605 | K28: =+F7 -> 16950 | M28: =+H28/5 -> 2500
A29: PLACENTA | B29: TRUE | C29: FALSE | D29: FALSE | E29: FALSE | F29: FALSE | G29: CB | H29: =+$B$11+H13 -> 7000 | I29: =+$B$12 -> 390 | J29: =+I29*10*(100%-15%) -> 3315 | K29: =+I29*20*(100%-25%) -> 5850 | M29: =+H29/5 -> 1400
A30: PLACENTA | B30: TRUE | C30: TRUE | D30: FALSE | E30: FALSE | F30: FALSE | G30: CB + PB | H30: =+$B$11+$C$11+H13 -> 8000 | I30: =+$B$12+$C$12 -> 530 | J30: =+I30*10*(100%-15%) -> 4505 | K30: =+I30*20*(100%-25%) -> 7950 | M30: =+H30/5 -> 1600
A31: PLACENTA | B31: TRUE | C31: TRUE | D31: FALSE | E31: TRUE | F31: FALSE | G31: CB + PB + T (PB) | H31: =+$B$11+$C$11+$E$11+H13 -> 10500 | I31: =+$B$12+$C$12+$E$12 -> 670 | J31: =+I31*10*(100%-15%) -> 5695 | K31: =+I31*20*(100%-25%) -> 10050 | M31: =+H31/5 -> 2100
A32: PLACENTA | B32: TRUE | C32: FALSE | D32: TRUE | E32: FALSE | F32: FALSE | G32: CB + T (CB) | H32: =+$B$11+$D$11+H13 -> 9000 | I32: =+$B$12+$D$12 -> 530 | J32: =+I32*10*(100%-15%) -> 4505 | K32: =+I32*20*(100%-25%) -> 7950 | M32: =+H32/5 -> 1800
A33: PLACENTA | B33: FALSE | C33: TRUE | D33: FALSE | E33: FALSE | F33: FALSE | G33: PB | H33: =+$C$11+H13 -> 3500 | I33: =+$C$12 -> 140 | J33: =+I33*10*(100%-15%) -> 1190 | K33: =+I33*20*(100%-25%) -> 2100 | M33: =+H33/5 -> 700
A34: PLACENTA | B34: FALSE | C34: TRUE | D34: FALSE | E34: TRUE | F34: FALSE | G34: PB+T (PB) | H34: =+$C$11+$E$11+H13 -> 6000 | I34: =+$C$12+$E$12 -> 280 | J34: =+I34*10*(100%-15%) -> 2380 | K34: =+I34*20*(100%-25%) -> 4200 | M34: =+H34/5 -> 1200
A35: PLACENTA | B35: FALSE | C35: FALSE | D35: FALSE | E35: TRUE | F35: FALSE | G35: T (PB) | H35: =+$E$11+H13 -> 5000 | I35: =+$E$12 -> 140 | J35: =+I35*10*(100%-15%) -> 1190 | K35: =+I35*20*(100%-25%) -> 2100 | L35: price for collection is written in contract in value 3 000 RON | M35: =+H35/5 -> 1000
A36: PLACENTA | B36: FALSE | C36: FALSE | D36: FALSE | E36: FALSE | F36: TRUE | G36: PL | H36: =+$F$11+H13 -> 4500 | I36: =+$F$12 -> 460 | J36: =+I36*10*(100%-15%) -> 3910 | K36: =+I36*20*(100%-25%) -> 6900 | L36: price for collection is written in contract in value 8 000 RON | M36: =+H36/5 -> 900
A37: PLACENTA | B37: TRUE | C37: FALSE | D37: FALSE | E37: FALSE | F37: TRUE | G37: CB+PL | H37: =+$B$11+$F$11+H13 -> 9000 | I37: =+$B$12+$F$12 -> 850 | J37: =+I37*10*(100%-15%) -> 7225 | K37: =+I37*20*(100%-25%) -> 12750 | M37: =+H37/5 -> 1800
A38: PLACENTA | B38: TRUE | C38: TRUE | D38: FALSE | E38: FALSE | F38: TRUE | G38: CB+PB+PL | H38: =+$B$11+$C$11+$F$11+H13 -> 10000 | I38: =+$B$12+$C$12+$F$12 -> 990 | J38: =+I38*10*(100%-15%) -> 8415 | K38: =+I38*20*(100%-25%) -> 14850 | M38: =+H38/5 -> 2000
A39: PLACENTA | B39: TRUE | C39: FALSE | D39: FALSE | E39: TRUE | F39: TRUE | G39: CB+T(PB)+PL | H39: =+$B$11+$E$11+$F$11+H13 -> 11500 | I39: =+$B$12+$E$12+$F$12 -> 990 | J39: =+I39*10*(100%-15%) -> 8415 | K39: =+I39*20*(100%-25%) -> 14850 | M39: =+H39/5 -> 2300
A40: PLACENTA | B40: FALSE | C40: TRUE | D40: FALSE | E40: FALSE | F40: TRUE | G40: PB+PL | H40: =+$C$11+$F$11+H13 -> 5500 | I40: =+$C$12+$F$12 -> 600 | J40: =+I40*10*(100%-15%) -> 5100 | K40: =+I40*20*(100%-25%) -> 9000 | M40: =+H40/5 -> 1100
A41: PLACENTA | B41: FALSE | C41: TRUE | D41: FALSE | E41: TRUE | F41: TRUE | G41: PB+T(PB)+PL | H41: =+$C$11+$E$11+$F$11+H13 -> 8000 | I41: =+$C$12+$E$12+$F$12 -> 740 | J41: =+I41*10*(100%-15%) -> 6290 | K41: =+I41*20*(100%-25%) -> 11100 | M41: =+H41/5 -> 1600
A42: PLACENTA | B42: FALSE | C42: FALSE | D42: FALSE | E42: TRUE | F42: TRUE | G42: T(PB)+PL | H42: =+$E$11+$F$11+H13 -> 7000 | I42: =+$E$12+$F$12 -> 600 | J42: =+I42*10*(100%-15%) -> 5100 | K42: =+I42*20*(100%-25%) -> 9000 | M42: =+H42/5 -> 1400
A43: * collection of blood (CB+PB) <20ml = discount 2000 RON
A44: ** CONTAMINATION = discount 100% from collection fee for contaminated item
A45: *** storage fee depend on REAL stored product (independent from volume or contamination)

Sheet HU
A1: HUNGARY
A3: PRICE LIST (from 1.1.2025) | B3: Classic | C3: Premium | D3: Cl.+Tissue | E3: PR.+Tissue | F3: Placenta | J3: CB* | K3: cord blood
B4: =+'COLLECTION PRICE'!C31 -> 560000 | C4: =+'COLLECTION PRICE'!D31 -> 640000 | D4: =+'COLLECTION PRICE'!E31 -> 720000 | E4: =+'COLLECTION PRICE'!F31 -> 840000 | G4: Collection | J4: PB | K4: placental blood
B5: =+'STORAGE PRICE'!C56 -> 32120 | C5: =+'STORAGE PRICE'!D56 -> 41490 | D5: =+'STORAGE PRICE'!E56 -> 40140 | E5: =+'STORAGE PRICE'!F56 -> 49510 | G5: 1 Year storage | J5: T (CB) | K5: cord tissue
B6: =+'STORAGE PRICE'!C57 -> 192720 | C6: =+'STORAGE PRICE'!D57 -> 248940 | D6: =+'STORAGE PRICE'!E57 -> 240840 | E6: =+'STORAGE PRICE'!F57 -> 297060 | G6: 10 Years storage | J6: T (PB) | K6: cord tissue
B7: =+'STORAGE PRICE'!C58 -> 321200 | C7: =+'STORAGE PRICE'!D58 -> 414900 | D7: =+'STORAGE PRICE'!E58 -> 401400 | E7: =+'STORAGE PRICE'!F58 -> 495100 | G7: 20 Years storage | J7: PL | K7: placenta
A9: Failed Collection or Contamination
A10: Product | B10: CB* | C10: PB | D10: T (CB) | E10: T (PB) | F10: PL | H10: Discounted | L10: plati v pripade jednotnej zmluvy CBC AG na odber krv aj tkanivo
A11: Price - collection | B11: =+B4-H13 -> 360000 | C11: =+C4-B4 -> 80000 | D11: =+D4-B4 -> 160000 | E11: =+E4-C4 -> 200000 | G11: Product | H11: price | J11: 40% discount | K11: 50% discount | L11: aktualne sa pouzivaju dve zmluvy: samostatne pre krv (CBC AG) a samostatne pre tkanivo (EC v hodnote 240 000 HUF) | M11: Collection
A12: Price - storage | B12: =+B5 -> 32120 | C12: =+C5-B5 -> 9370 | D12: =+D5-B12 -> 8020 | E12: =+E5-C5 -> 8020 | G12: adjustment | H12: COLLECTION | I12: 1 YEAR STORAGE | J12: 10 YEAR STORAGE | K12: 20 YEAR STORAGE | L12: aktualne sa pouzivanju zlavy 10 rocne skladne 40% a 20 rocne skladne 50% (standard CBC GROUP je 15% a 25%) | M12: in EUR
A13: FLAAT FEE | B13: FALSE | C13: FALSE | D13: FALSE | E13: FALSE | F13: FALSE | G13: ALL | H13: 200000 | M13: =+H13/400 -> 500
A14: Classic | B14: TRUE | C14: FALSE | D14: FALSE | E14: FALSE | F14: FALSE | G14: Classic | H14: =+B4 -> 560000 | I14: =+B5 -> 32120 | J14: =+B6 -> 192720 | K14: =+B7 -> 321200 | M14: =+H14/400 -> 1400
A15: Premium | B15: TRUE | C15: TRUE | D15: FALSE | E15: FALSE | F15: FALSE | G15: Premium | H15: =+C4 -> 640000 | I15: =+C5 -> 41490 | J15: =+C6 -> 248940 | K15: =+C7 -> 414900 | M15: =+H15/400 -> 1600
A16: Premium | B16: TRUE | C16: FALSE | D16: FALSE | E16: FALSE | F16: FALSE | G16: CB | H16: =+$B$11+H13 -> 560000 | I16: =+$B$12 -> 32120 | J16: =+I16*10*(100%-40%) -> 192720 | K16: =+I16*20*(100%-50%) -> 321200 | M16: =+H16/400 -> 1400
A17: Premium | B17: FALSE | C17: TRUE | D17: FALSE | E17: FALSE | F17: FALSE | G17: PB | H17: =+$C$11+H13 -> 280000 | I17: =+$C$12 -> 9370 | J17: =+I17*10*(100%-40%) -> 56220 | K17: =+I17*20*(100%-50%) -> 93700 | M17: =+H17/400 -> 700
A18: Classic+Tissue | B18: TRUE | C18: FALSE | D18: FALSE | E18: FALSE | F18: FALSE | G18: Classic+Tissue | H18: =+D4 -> 720000 | I18: =+D5 -> 40140 | J18: =+D6 -> 240840 | K18: =+D7 -> 401400 | M18: =+H18/400 -> 1800
A19: Classic+Tissue | B19: TRUE | C19: FALSE | D19: FALSE | E19: FALSE | F19: FALSE | G19: CB | H19: =+$B$11+H13 -> 560000 | I19: =+$B$12 -> 32120 | J19: =+I19*10*(100%-40%) -> 192720 | K19: =+I19*20*(100%-50%) -> 321200 | M19: =+H19/400 -> 1400
A20: Classic+Tissue | B20: FALSE | C20: FALSE | D20: TRUE | E20: FALSE | F20: FALSE | G20: T (CB) | H20: =+$D$11+H13 -> 360000 | I20: =+$D$12 -> 8020 | J20: =+I20*10*(100%-40%) -> 48120 | K20: =+I20*20*(100%-50%) -> 80200 | M20: =+H20/400 -> 900
A21: Premium+Tissue | B21: TRUE | C21: TRUE | D21: TRUE | E21: FALSE | F21: FALSE | G21: Premium+Tissue | H21: =+E4 -> 840000 | I21: =+E5 -> 49510 | J21: =+E6 -> 297060 | K21: =+E7 -> 495100 | M21: =+H21/400 -> 2100
A22: Premium+Tissue | B22: TRUE | C22: FALSE | D22: FALSE | E22: FALSE | F22: FALSE | G22: CB | H22: =+$B$11+H13 -> 560000 | I22: =+$B$12 -> 32120 | J22: =+I22*10*(100%-40%) -> 192720 | K22: =+I22*20*(100%-50%) -> 321200 | M22: =+H22/400 -> 1400
A23: Premium+Tissue | B23: TRUE | C23: TRUE | D23: FALSE | E23: TRUE | F23: FALSE | G23: CB + PB | H23: =+$B$11+$C$11+H13 -> 640000 | I23: =+$B$12+$C$12 -> 41490 | J23: =+I23*10*(100%-40%) -> 248940 | K23: =+I23*20*(100%-50%) -> 414900 | M23: =+H23/400 -> 1600
A24: Premium+Tissue | B24: TRUE | C24: FALSE | D24: TRUE | E24: FALSE | F24: FALSE | G24: CB + T (CB) | H24: =+$B$11+$D$11+H13 -> 720000 | I24: =+$B$12+$D$12 -> 40140 | J24: =+I24*10*(100%-40%) -> 240840 | K24: =+I24*20*(100%-50%) -> 401400 | M24: =+H24/400 -> 1800
A25: Premium+Tissue | B25: FALSE | C25: TRUE | D25: FALSE | E25: FALSE | F25: FALSE | G25: PB | H25: =+$C$11+H13 -> 280000 | I25: =+$C$12 -> 9370 | J25: =+I25*10*(100%-40%) -> 56220 | K25: =+I25*20*(100%-50%) -> 93700 | M25: =+H25/400 -> 700
A26: Premium+Tissue | B26: FALSE | C26: TRUE | D26: FALSE | E26: TRUE | F26: FALSE | G26: PB+T (PB) | H26: =+$C$11+$E$11+H13 -> 480000 | I26: =+$C$12+$E$12 -> 17390 | J26: =+I26*10*(100%-40%) -> 104340 | K26: =+I26*20*(100%-50%) -> 173900 | M26: =+H26/400 -> 1200
A27: Premium+Tissue | B27: FALSE | C27: FALSE | D27: FALSE | E27: TRUE | F27: FALSE | G27: T (PB) | H27: =+$E$11+H13 -> 400000 | I27: =+$E$12 -> 8020 | J27: =+I27*10*(100%-40%) -> 48120 | K27: =+I27*20*(100%-50%) -> 80200 | M27: =+H27/400 -> 1000
A28: PLACENTA | B28: TRUE | C28: TRUE | D28: FALSE | E28: TRUE | F28: TRUE | G28: Placenta | H28: =+F4 -> 0 | I28: =+F5 -> 0 | J28: =+F6 -> 0 | K28: =+F7 -> 0 | M28: =+H28/400 -> 0
A29: PLACENTA | B29: TRUE | C29: FALSE | D29: FALSE | E29: FALSE | F29: FALSE | G29: CB | M29: =+H29/400 -> 0
A30: PLACENTA | B30: TRUE | C30: TRUE | D30: FALSE | E30: FALSE | F30: FALSE | G30: CB + PB | M30: =+H30/400 -> 0
A31: PLACENTA | B31: TRUE | C31: TRUE | D31: FALSE | E31: TRUE | F31: FALSE | G31: CB + PB + T (PB) | M31: =+H31/400 -> 0
A32: PLACENTA | B32: TRUE | C32: FALSE | D32: TRUE | E32: FALSE | F32: FALSE | G32: CB + T (CB) | M32: =+H32/400 -> 0
A33: PLACENTA | B33: FALSE | C33: TRUE | D33: FALSE | E33: FALSE | F33: FALSE | G33: PB | M33: =+H33/400 -> 0
A34: PLACENTA | B34: FALSE | C34: TRUE | D34: FALSE | E34: TRUE | F34: FALSE | G34: PB+T (PB) | M34: =+H34/400 -> 0
A35: PLACENTA | B35: FALSE | C35: FALSE | D35: FALSE | E35: TRUE | F35: FALSE | G35: T (PB) | M35: =+H35/400 -> 0
A36: PLACENTA | B36: FALSE | C36: FALSE | D36: FALSE | E36: FALSE | F36: TRUE | G36: PL | M36: =+H36/400 -> 0
A37: PLACENTA | B37: TRUE | C37: FALSE | D37: FALSE | E37: FALSE | F37: TRUE | G37: CB+PL | M37: =+H37/400 -> 0
A38: PLACENTA | B38: TRUE | C38: TRUE | D38: FALSE | E38: FALSE | F38: TRUE | G38: CB+PB+PL | M38: =+H38/400 -> 0
A39: PLACENTA | B39: TRUE | C39: FALSE | D39: FALSE | E39: TRUE | F39: TRUE | G39: CB+T(PB)+PL | M39: =+H39/400 -> 0
A40: PLACENTA | B40: FALSE | C40: TRUE | D40: FALSE | E40: FALSE | F40: TRUE | G40: PB+PL | M40: =+H40/400 -> 0
... A42: PLACENTA | B42: FALSE | C42: FALSE | D42: FALSE | E42: TRUE | F42: TRUE | G42: T(PB)+PL | M42: =+H42/400 -> 0
A43: * collection CB <20ml = discount 160 000 HUF
A44: ** CONTAMINATION = discount 100% from collection fee for contaminated item
A45: *** storage fee depend on REAL stored product (independent from volume or contamination)

Sheet AT
A1: AUSTRIA
A3: PRICE LIST (from 1.1.2025) | B3: Classic | C3: Premium | D3: Cl.+Tissue | E3: PR.+Tissue | F3: Placenta | J3: CB* | K3: cord blood
B4: =+'COLLECTION PRICE'!C37 -> 1490 | C4: =+'COLLECTION PRICE'!D37 -> 1790 | D4: =+'COLLECTION PRICE'!E37 -> 2190 | E4: =+'COLLECTION PRICE'!F37 -> 2490 | G4: Collection | J4: PB | K4: placental blood
B5: =+'STORAGE PRICE'!C41 -> 67.80253 | C5: =+'STORAGE PRICE'!D41 -> 79.294485 | D5: =+'STORAGE PRICE'!E41 -> 90.786439 | E5: =+'STORAGE PRICE'!F41 -> 102.27839 | G5: 1 Year storage | J5: T (CB) | K5: cord tissue
B6: =+'STORAGE PRICE'!C42 -> 321.77472 | C6: =+'STORAGE PRICE'!D42 -> 376.9361 | D6: =+'STORAGE PRICE'!E42 -> 430.94829 | E6: =+'STORAGE PRICE'!F42 -> 486.10967 | G6: 5 Years storage | J6: T (PB) | K6: cord tissue
B7: =+'STORAGE PRICE'!C43 -> 610.22277 | C7: =+'STORAGE PRICE'!D43 -> 713.65036 | D7: =+'STORAGE PRICE'!E43 -> 817.07795 | E7: =+'STORAGE PRICE'!F43 -> 920.50554 | G7: 10 Years storage | J7: PL | K7: placenta
A9: Failed Collection or Contamination
A10: Product | B10: CB* | C10: PB | D10: T (CB) | E10: T (PB) | F10: PL | H10: Discounted
A11: Price - collection | B11: =+B4-H13 -> 990 | C11: =+C4-B4 -> 300 | D11: =+D4-B4 -> 700 | E11: =+E4-C4 -> 700 | G11: Product | H11: price | J11: 5% discount | K11: 10% discount
A12: Price - storage | B12: =+B5 -> 67.80253 | C12: =+C5-B5 -> 11.491954 | D12: =+D5-B12 -> 22.983909 | E12: =+E5-C5 -> 22.983909 | G12: adjustment | H12: COLLECTION | I12: 1 YEAR STORAGE | J12: 5 YEAR STORAGE | K12: 10 YEAR STORAGE
A13: ALL PRODUCS | B13: FALSE | C13: FALSE | D13: FALSE | E13: FALSE | F13: FALSE | G13: ALL | H13: 500
A14: Classic | B14: TRUE | C14: FALSE | D14: FALSE | E14: FALSE | F14: FALSE | G14: Classic | H14: =+B4 -> 1490 | I14: =+B5 -> 67.80253 | J14: =+B6 -> 321.77472 | K14: =+B7 -> 610.22277
A15: Premium | B15: TRUE | C15: TRUE | D15: FALSE | E15: FALSE | F15: FALSE | G15: Premium | H15: =+C4 -> 1790 | I15: =+C5 -> 79.294485 | J15: =+C6 -> 376.9361 | K15: =+C7 -> 713.65036
A16: Premium | B16: TRUE | C16: FALSE | D16: FALSE | E16: FALSE | F16: FALSE | G16: CB | H16: =+$B$11+H13 -> 1490 | I16: =+$B$12 -> 67.80253 | J16: =+I16*5*(100%-10%) -> 305.11139 | K16: =+I16*10*(100%-15%) -> 576.32151
A17: Premium | B17: FALSE | C17: TRUE | D17: FALSE | E17: FALSE | F17: FALSE | G17: PB | H17: =+$C$11+H13 -> 800 | I17: =+$C$12 -> 11.491954 | J17: =+I17*5*(100%-10%) -> 51.713794 | K17: =+I17*10*(100%-15%) -> 97.681612
A18: Classic+Tissue | B18: TRUE | C18: FALSE | D18: TRUE | E18: FALSE | F18: FALSE | G18: Classic+Tissue | H18: =+D4 -> 2190 | I18: =+D5 -> 90.786439 | J18: =+D6 -> 430.94829 | K18: =+D7 -> 817.07795
A19: Classic+Tissue | B19: TRUE | C19: FALSE | D19: FALSE | E19: FALSE | F19: FALSE | G19: CB | H19: =+$B$11+H13 -> 1490 | I19: =+$B$12 -> 67.80253 | J19: =+I19*5*(100%-10%) -> 305.11139 | K19: =+I19*10*(100%-15%) -> 576.32151
A20: Classic+Tissue | B20: FALSE | C20: FALSE | D20: TRUE | E20: FALSE | F20: FALSE | G20: T (CB) | H20: =+$D$11+H13 -> 1200 | I20: =+$D$12 -> 22.983909 | J20: =+I20*5*(100%-10%) -> 103.42759 | K20: =+I20*10*(100%-15%) -> 195.36322
A21: Premium+Tissue | B21: TRUE | C21: TRUE | D21: TRUE | E21: FALSE | F21: FALSE | G21: Premium+Tissue | H21: =+E4 -> 2490 | I21: =+E5 -> 102.27839 | J21: =+E6 -> 486.10967 | K21: =+E7 -> 920.50554
A22: Premium+Tissue | B22: TRUE | C22: FALSE | D22: FALSE | E22: FALSE | F22: FALSE | G22: CB | H22: =+$B$11+H13 -> 1490 | I22: =+$B$12 -> 67.80253 | J22: =+I22*5*(100%-10%) -> 305.11139 | K22: =+I22*10*(100%-15%) -> 576.32151
A23: Premium+Tissue | B23: TRUE | C23: TRUE | D23: FALSE | E23: FALSE | F23: FALSE | G23: CB + PB | H23: =+$B$11+$C$11+H13 -> 1790 | I23: =+$B$12+$C$12 -> 79.294485 | J23: =+I23*5*(100%-10%) -> 356.82518 | K23: =+I23*10*(100%-15%) -> 674.00312
A24: Premium+Tissue | B24: TRUE | C24: FALSE | D24: TRUE | E24: FALSE | F24: FALSE | G24: CB + T (CB) | H24: =+$B$11+$D$11+H13 -> 2190 | I24: =+$B$12+$D$12 -> 90.786439 | J24: =+I24*5*(100%-10%) -> 408.53898 | K24: =+I24*10*(100%-15%) -> 771.68473
A25: Premium+Tissue | B25: FALSE | C25: TRUE | D25: FALSE | E25: FALSE | F25: FALSE | G25: PB | H25: =+$C$11+H13 -> 800 | I25: =+$C$12 -> 11.491954 | J25: =+I25*5*(100%-10%) -> 51.713794 | K25: =+I25*10*(100%-15%) -> 97.681612
A26: Premium+Tissue | B26: FALSE | C26: TRUE | D26: FALSE | E26: TRUE | F26: FALSE | G26: PB+T (PB) | H26: =+$C$11+$E$11+H13 -> 1500 | I26: =+$C$12+$E$12 -> 34.475863 | J26: =+I26*5*(100%-10%) -> 155.14138 | K26: =+I26*10*(100%-15%) -> 293.04484
A27: Premium+Tissue | B27: FALSE | C27: FALSE | D27: FALSE | E27: TRUE | F27: FALSE | G27: T (PB) | H27: =+$E$11+H13 -> 1200 | I27: =+$E$12 -> 22.983909 | J27: =+I27*5*(100%-10%) -> 103.42759 | K27: =+I27*10*(100%-15%) -> 195.36322
A28: PLACENTA | B28: TRUE | C28: TRUE | D28: FALSE | E28: TRUE | F28: TRUE | G28: Placenta | H28: =+F4 -> 0 | I28: =+F5 -> 0 | J28: =+F6 -> 0 | K28: =+F7 -> 0
A29: PLACENTA | B29: TRUE | C29: FALSE | D29: FALSE | E29: FALSE | F29: FALSE | G29: Classic
A30: PLACENTA | B30: TRUE | C30: TRUE | D30: FALSE | E30: FALSE | F30: FALSE | G30: Premium
A31: PLACENTA | B31: TRUE | C31: TRUE | D31: FALSE | E31: TRUE | F31: FALSE | G31: Premium+Tissue
A32: PLACENTA | B32: TRUE | C32: FALSE | D32: TRUE | E32: FALSE | F32: FALSE | G32: Classic+Tissue
A33: PLACENTA | B33: FALSE | C33: TRUE | D33: FALSE | E33: FALSE | F33: FALSE | G33: PB
A34: PLACENTA | B34: FALSE | C34: TRUE | D34: FALSE | E34: TRUE | F34: FALSE | G34: PB+T (PB)
A35: PLACENTA | B35: FALSE | C35: FALSE | D35: FALSE | E35: TRUE | F35: FALSE | G35: T (PB)
A36: PLACENTA | B36: FALSE | C36: FALSE | D36: FALSE | E36: FALSE | F36: TRUE | G36: PL
A37: PLACENTA | B37: TRUE | C37: FALSE | D37: FALSE | E37: FALSE | F37: TRUE | G37: CB+PL
A38: PLACENTA | B38: TRUE | C38: TRUE | D38: FALSE | E38: FALSE | F38: TRUE | G38: CB+PB+PL
A39: PLACENTA | B39: TRUE | C39: FALSE | D39: FALSE | E39: TRUE | F39: TRUE | G39: CB+T(PB)+PL
A40: PLACENTA | B40: FALSE | C40: TRUE | D40: FALSE | E40: FALSE | F40: TRUE | G40: PB+PL
... A42: PLACENTA | B42: FALSE | C42: FALSE | D42: FALSE | E42: TRUE | F42: TRUE | G42: T(PB)+PL
A43: * collection CB <20ml = discount 400 EUR

Sheet ITA
A1: ITALY
A3: PRICE LIST (from 1.1.2025) | B3: Classic | C3: Premium | D3: Cl.+Tissue | E3: PR.+Tissue | F3: Placenta | J3: CB* | K3: cord blood
B4: =+'COLLECTION PRICE'!C40 -> 1090 | C4: =+'COLLECTION PRICE'!D40 -> 1290 | D4: =+'COLLECTION PRICE'!E40 -> 1390 | E4: =+'COLLECTION PRICE'!F40 -> 1590 | G4: Collection | J4: PB | K4: placental blood
B5: =+'STORAGE PRICE'!C44 -> 65.015013 | C5: =+'STORAGE PRICE'!D44 -> 86.686684 | D5: =+'STORAGE PRICE'!E44 -> 86.686684 | E5: =+'STORAGE PRICE'!F44 -> 92.104602 | G5: 1 Year storage | J5: T (CB) | K5: cord tissue
B6: =+'STORAGE PRICE'!C45 -> 541.79177 | C6: =+'STORAGE PRICE'!D45 -> 639.31429 | D6: =+'STORAGE PRICE'!E45 -> 726.00098 | E6: =+'STORAGE PRICE'!F45 -> 758.50848 | G6: 10 Years storage | J6: T (PB) | K6: cord tissue
B7: =+'STORAGE PRICE'!C46 -> 975.22519 | C7: =+'STORAGE PRICE'!D46 -> 1083.5835 | D7: =+'STORAGE PRICE'!E46 -> 1191.9419 | E7: =+'STORAGE PRICE'!F46 -> 1300.3003 | G7: 20 Years storage | J7: PL | K7: placenta
A9: Failed Collection or Contamination
A10: Product | B10: CB* | C10: PB | D10: T (CB) | E10: T (PB) | F10: PL | H10: Discounted | J10: various % discount | K10: various % discount | L10: absolutne nelogicke ceny a percentualne zlavy pri viacrocnom skladnom
A11: Price - collection | B11: =+B4 -> 1090 | C11: =+C4-B4 -> 200 | D11: =+D4-B4 -> 300 | E11: =+E4-C4 -> 300 | F11: =+F4-E4 -> -1590 | G11: Product | H11: price
A12: Price - storage | B12: =+B5 -> 65.015013 | C12: =+C5-B5 -> 21.671671 | D12: =+D5-B12 -> 21.671671 | E12: =+E5-C5 -> 5.4179177 | F12: =+F5-E5 -> -92.104602 | G12: adjustment | H12: COLLECTION | I12: 1 YEAR STORAGE | J12: 10 YEAR STORAGE | K12: 20 YEAR STORAGE
A13: ALL PRODUCS | B13: FALSE | C13: FALSE | D13: FALSE | E13: FALSE | F13: FALSE | G13: VIP | H13: 1 | L13: stare ceny, nereflektuju aktualnu cenovu politiku CBC GROUP
A14: Classic | B14: TRUE | C14: FALSE | D14: FALSE | E14: FALSE | F14: FALSE | G14: Classic | H14: =+B4 -> 1090 | I14: =+B5 -> 65.015013 | J14: =+B6 -> 541.79177 | K14: =+B7 -> 975.22519
A15: Premium | B15: TRUE | C15: TRUE | D15: FALSE | E15: FALSE | F15: FALSE | G15: Premium | H15: =+C4 -> 1290 | I15: =+C5 -> 86.686684 | J15: =+C6 -> 639.31429 | K15: =+C7 -> 1083.5835
A16: Premium | B16: TRUE | C16: FALSE | D16: FALSE | E16: FALSE | F16: FALSE | G16: CB | H16: =+$B$11 -> 1090 | I16: =+$B$12 -> 65.015013 | J16: =+$J$14 -> 541.79177 | K16: =+$K$14 -> 975.22519
A17: Premium | B17: FALSE | C17: TRUE | D17: FALSE | E17: FALSE | F17: FALSE | G17: PB | H17: =+$C$11 -> 200 | I17: =+$C$12 -> 21.671671 | J17: =+I17*10*85% -> 184.2092 | K17: =+I17*20*75% -> 325.07507
A18: Classic+Tissue | B18: TRUE | C18: FALSE | D18: TRUE | E18: FALSE | F18: FALSE | G18: Classic+Tissue | H18: =+D4 -> 1390 | I18: =+D5 -> 86.686684 | J18: =+D6 -> 726.00098 | K18: =+D7 -> 1191.9419
A19: Classic+Tissue | B19: TRUE | C19: FALSE | D19: FALSE | E19: FALSE | F19: FALSE | G19: CB | H19: =+$B$11 -> 1090 | I19: =+$B$12 -> 65.015013 | J19: =+$J$14 -> 541.79177 | K19: =+$K$14 -> 975.22519
A20: Classic+Tissue | B20: FALSE | C20: FALSE | D20: TRUE | E20: FALSE | F20: FALSE | G20: T (CB) | H20: =+$D$11 -> 300 | I20: =+$D$12 -> 21.671671 | J20: =+I20*10*85% -> 184.2092 | K20: =+I20*20*75% -> 325.07507
A21: Premium+Tissue | B21: TRUE | C21: TRUE | D21: TRUE | E21: FALSE | F21: FALSE | G21: Premium+Tissue | H21: =+E4 -> 1590 | I21: =+E5 -> 92.104602 | J21: =+E6 -> 758.50848 | K21: =+E7 -> 1300.3003
A22: Premium+Tissue | B22: TRUE | C22: FALSE | D22: FALSE | E22: FALSE | F22: FALSE | G22: CB | H22: =+$B$11 -> 1090 | I22: =+$B$12 -> 65.015013 | J22: =+$J$14 -> 541.79177 | K22: =+$K$14 -> 975.22519
A23: Premium+Tissue | B23: TRUE | C23: TRUE | D23: FALSE | E23: FALSE | F23: FALSE | G23: CB + PB | H23: =+$B$11+$C$11 -> 1290 | I23: =+$B$12+$C$12 -> 86.686684 | J23: =+$J$15 -> 639.31429 | K23: =+$K$15 -> 1083.5835
A24: Premium+Tissue | B24: TRUE | C24: FALSE | D24: TRUE | E24: FALSE | F24: FALSE | G24: CB + T (CB) | H24: =+$B$11+$D$11 -> 1390 | I24: =+$B$12+$D$12 -> 86.686684 | J24: =+$J$18 -> 726.00098 | K24: =+$K$18 -> 1191.9419
A25: Premium+Tissue | B25: FALSE | C25: TRUE | D25: FALSE | E25: FALSE | F25: FALSE | G25: PB | H25: =+$C$11 -> 200 | I25: =+$C$12 -> 21.671671 | J25: =+I25*10*85% -> 184.2092 | K25: =+I25*20*75% -> 325.07507
A26: Premium+Tissue | B26: FALSE | C26: TRUE | D26: FALSE | E26: TRUE | F26: FALSE | G26: PB+T (PB) | H26: =+$C$11+$E$11 -> 500 | I26: =+$C$12+$E$12 -> 27.089589 | J26: =+I26*10*85% -> 230.2615 | K26: =+I26*20*75% -> 406.34383
A27: Premium+Tissue | B27: FALSE | C27: FALSE | D27: FALSE | E27: TRUE | F27: FALSE | G27: T (PB) | H27: =+$E$11 -> 300 | I27: =+$E$12 -> 5.4179177 | J27: =+$J$20 -> 184.2092 | K27: =+$K$20 -> 325.07507
A28: PLACENTA | B28: TRUE | C28: TRUE | D28: FALSE | E28: TRUE | F28: TRUE | G28: Placenta | H28: =+F4 -> 0 | I28: =+F5 -> 0 | J28: =+F6 -> 0 | K28: =+F7 -> 0
A29: PLACENTA | B29: TRUE | C29: FALSE | D29: FALSE | E29: FALSE | F29: FALSE | G29: Classic
A30: PLACENTA | B30: TRUE | C30: TRUE | D30: FALSE | E30: FALSE | F30: FALSE | G30: Premium
A31: PLACENTA | B31: TRUE | C31: TRUE | D31: FALSE | E31: TRUE | F31: FALSE | G31: Premium+Tissue
A32: PLACENTA | B32: TRUE | C32: FALSE | D32: TRUE | E32: FALSE | F32: FALSE | G32: Classic+Tissue
A33: PLACENTA | B33: FALSE | C33: TRUE | D33: FALSE | E33: FALSE | F33: FALSE | G33: PB
A34: PLACENTA | B34: FALSE | C34: TRUE | D34: FALSE | E34: TRUE | F34: FALSE | G34: PB+T (PB)
A35: PLACENTA | B35: FALSE | C35: FALSE | D35: FALSE | E35: TRUE | F35: FALSE | G35: T (PB)
A36: PLACENTA | B36: FALSE | C36: FALSE | D36: FALSE | E36: FALSE | F36: TRUE | G36: PL
A37: PLACENTA | B37: TRUE | C37: FALSE | D37: FALSE | E37: FALSE | F37: TRUE | G37: CB+PL
A38: PLACENTA | B38: TRUE | C38: TRUE | D38: FALSE | E38: FALSE | F38: TRUE | G38: CB+PB+PL
A39: PLACENTA | B39: TRUE | C39: FALSE | D39: FALSE | E39: TRUE | F39: TRUE | G39: CB+T(PB)+PL
A40: PLACENTA | B40: FALSE | C40: TRUE | D40: FALSE | E40: FALSE | F40: TRUE | G40: PB+PL
... A42: PLACENTA | B42: FALSE | C42: FALSE | D42: FALSE | E42: TRUE | F42: TRUE | G42: T(PB)+PL
A43: * collection CB <20ml = discount 400 EUR

Sheet cost
B3: SK | L3: RO | V3: CZ | AF3: HU | AP3: AT | AW3: ITA
B4: Classic | C4: Premium | D4: CB+T | E4: PB+T | F4: PB+T+P | H4: PB | I4: T | J4: PL | L4: Classic | M4: Premium | N4: CB+T | O4: PB+T | P4: PB+T+P | R4: PB | S4: T | T4: PL | V4: Classic | W4: Premium | X4: CB+T | Y4: PB+T | Z4: PB+T+P | AB4: PB | AC4: T | AD4: PL | AF4: Classic | AG4: Premium | AH4: CB+T | AI4: PB+T | AJ4: PB+T+P | AL4: PB | AM4: T | AN4: PL | AP4: Classic | AQ4: Premium | AR4: CB+T | AS4: PB+T | AT4: PB+T+P | AW4: Classic | AX4: Premium | AY4: CB+T | AZ4: PB+T | BA4: PB+T+P
A5: Gross revenue - new prices | B5: 1400 | C5: 1600 | D5: 1800 | E5: 2100 | F5: 2500 | H5: =+SK!H17 -> 700 | I5: =+SK!H20 -> 900 | J5: =+SK!H36 -> 900 | L5: 1400 | M5: 1600 | N5: 1800 | O5: 2100 | P5: 2500 | R5: =+RO!H17/5 -> 700 | S5: =+RO!H20/5 -> 900 | T5: =+RO!H36/5 -> 900 | V5: 1400 | W5: 1600 | X5: 1800 | Y5: 2100 | Z5: 2500 | AB5: =+CZ!H17/25 -> 700 | AC5: =+CZ!H20/25 -> 900 | AD5: =+CZ!H36/25 -> 900 | AF5: 1400 | AG5: 1600 | AH5: 1800 | AI5: 2100 | AL5: =+HU!H17/400 -> 700 | AM5: =+HU!H20/400 -> 900 | AP5: 1490 | AQ5: 1790 | AR5: 2190 | AS5: 2490 | AW5: 1090 | AX5: 1290 | AY5: 1390 | AZ5: 1590
A6: discount (free collection/broker) | B6: =+$G$6*(B5) -> -140 | C6: =+$G$6*(C5) -> -160 | D6: =+$G$6*(D5) -> -180 | E6: =+$G$6*(E5) -> -210 | F6: =-5%*(F5) -> -125 | G6: -0.1 | H6: 0 | I6: 0 | J6: 0 | L6: =+$Q$6*(L5) -> -140 | M6: =+$Q$6*(M5) -> -160 | N6: =+$Q$6*(N5) -> -180 | O6: =+$Q$6*(O5) -> -210 | P6: =-5%*(P5) -> -125 | Q6: -0.1 | R6: 0 | S6: 0 | T6: 0 | V6: =+$AA$6*(V5) -> -140 | W6: =+$AA$6*(W5) -> -160 | X6: =+$AA$6*(X5) -> -180 | Y6: =+$AA$6*(Y5) -> -210 | Z6: =-5%*(Z5) -> -125 | AA6: -0.1 | AB6: 0 | AC6: 0 | AD6: 0 | AF6: =+$AK$6*(AF5) -> -140 | AG6: =+$AK$6*(AG5) -> -160 | AH6: =+$AK$6*(AH5) -> -180 | AI6: =+$AK$6*(AI5) -> -210 | AK6: -0.1 | AL6: 0 | AM6: 0 | AP6: =+$AU$6*(AP5) -> -149 | AQ6: =+$AU$6*(AQ5) -> -179 | AR6: =+$AU$6*(AR5) -> -219 | AS6: =+$AU$6*(AS5) -> -249 | AT6: =+$AU$9*(AT5) -> 0 | AU6: -0.1 | AW6: =+$BB$6*(AW5) -> -109 | AX6: =+$BB$6*(AX5) -> -129 | AY6: =+$BB$6*(AY5) -> -139 | AZ6: =+$BB$6*(AZ5) -> -159 | BA6: =+$BB$9*(BA5) -> 0 | BB6: -0.1
A7: Net revenue - client price | B7: =SUM(B5:B6) -> 1260 | C7: =SUM(C5:C6) -> 1440 | D7: =SUM(D5:D6) -> 1620 | E7: =SUM(E5:E6) -> 1890 | F7: =SUM(F5:F6) -> 2375 | H7: =SUM(H5:H6) -> 700 | I7: =SUM(I5:I6) -> 900 | J7: =SUM(J5:J6) -> 900 | L7: =SUM(L5:L6) -> 1260 | M7: =SUM(M5:M6) -> 1440 | N7: =SUM(N5:N6) -> 1620 | O7: =SUM(O5:O6) -> 1890 | P7: =SUM(P5:P6) -> 2375 | R7: =SUM(R5:R6) -> 700 | S7: =SUM(S5:S6) -> 900 | T7: =SUM(T5:T6) -> 900 | V7: =SUM(V5:V6) -> 1260 | W7: =SUM(W5:W6) -> 1440 | X7: =SUM(X5:X6) -> 1620 | Y7: =SUM(Y5:Y6) -> 1890 | Z7: =SUM(Z5:Z6) -> 2375 | AB7: =SUM(AB5:AB6) -> 700 | AC7: =SUM(AC5:AC6) -> 900 | AD7: =SUM(AD5:AD6) -> 900 | AF7: =SUM(AF5:AF6) -> 1260 | AG7: =SUM(AG5:AG6) -> 1440 | AH7: =SUM(AH5:AH6) -> 1620 | AI7: =SUM(AI5:AI6) -> 1890 | AJ7: =SUM(AJ5:AJ6) -> 0 | AL7: =SUM(AL5:AL6) -> 700 | AM7: =SUM(AM5:AM6) -> 900 | AN7: =SUM(AN5:AN6) -> 0 | AP7: =SUM(AP5:AP6) -> 1341 | AQ7: =SUM(AQ5:AQ6) -> 1611 | AR7: =SUM(AR5:AR6) -> 1971 | AS7: =SUM(AS5:AS6) -> 2241 | AT7: =SUM(AT5:AT6) -> 0 | AW7: =SUM(AW5:AW6) -> 981 | AX7: =SUM(AX5:AX6) -> 1161 | AY7: =SUM(AY5:AY6) -> 1251 | AZ7: =SUM(AZ5:AZ6) -> 1431 | BA7: =SUM(BA5:BA6) -> 0
A9: odmena broker/REP/CC (15% z net revenue) | B9: =+B7*$G9 -> -189 | C9: =+C7*$G9 -> -216 | D9: =+D7*$G9 -> -243 | E9: =+E7*$G9 -> -283.5 | F9: =+F7*$G9 -> -356.25 | G9: -0.15 | H9: =+C9 -> -216 | I9: =+E9 -> -283.5 | J9: =+F9 -> -356.25 | L9: =$Q$9*L7 -> -189 | M9: =$Q$9*M7 -> -216 | N9: =$Q$9*N7 -> -243 | O9: =$Q$9*O7 -> -283.5 | P9: =$Q$9*P7 -> -356.25 | Q9: -0.15 | R9: =+M9 -> -216 | S9: =+O9 -> -283.5 | T9: =+P9 -> -356.25 | V9: =+V7*$AA9 -> -189 | W9: =+W7*$AA9 -> -216 | X9: =+X7*$AA9 -> -243 | Y9: =+Y7*$AA9 -> -283.5 | Z9: =+Z7*$AA9 -> -356.25 | AA9: -0.15 | AB9: =+W9 -> -216 | AC9: =+Y9 -> -283.5 | AD9: =+Z9 -> -356.25 | AF9: =+AF7*$AK9 -> -189 | AG9: =+AG7*$AK9 -> -216 | AH9: =+AH7*$AK9 -> -243 | AI9: =+AI7*$AK9 -> -283.5 | AJ9: =+AJ7*$AK9 -> 0 | AK9: -0.15 | AL9: =+AG9 -> -216 | AM9: =+AI9 -> -283.5 | AN9: =+AJ9 -> 0 | AP9: =+$AU$14*(AP7) -> 0 | AQ9: =+$AU$14*(AQ7) -> 0 | AR9: =+$AU$14*(AR7) -> 0 | AS9: =+$AU$14*(AS7) -> 0 | AT9: =+$AU$14*(AT7) -> 0 | AU9: -0.15 | AW9: =+$BB$14*(AW7) -> 0 | AX9: =+$BB$14*(AX7) -> 0 | AY9: =+$BB$14*(AY7) -> 0 | AZ9: =+$BB$14*(AZ7) -> 0 | BA9: =+$BB$14*(BA7) -> 0 | BB9: -0.15
A10: Net revenue - CBC | B10: =+B5+B6+B9 -> 1071 | C10: =+C5+C6+C9 -> 1224 | D10: =+D5+D6+D9 -> 1377 | E10: =+E5+E6+E9 -> 1606.5 | F10: =+F5+F6+F9 -> 2018.75 | H10: =+H5+H6+H9 -> 484 | I10: =+I5+I6+I9 -> 616.5 | J10: =+J5+J6+J9 -> 543.75 | L10: =+L5+L6+L9 -> 1071 | M10: =+M5+M6+M9 -> 1224 | N10: =+N5+N6+N9 -> 1377 | O10: =+O5+O6+O9 -> 1606.5 | P10: =+P5+P6+P9 -> 2018.75 | R10: =+R5+R6+R9 -> 484 | S10: =+S5+S6+S9 -> 616.5 | T10: =+T5+T6+T9 -> 543.75 | V10: =+V5+V6+V9 -> 1071 | W10: =+W5+W6+W9 -> 1224 | X10: =+X5+X6+X9 -> 1377 | Y10: =+Y5+Y6+Y9 -> 1606.5 | Z10: =+Z5+Z6+Z9 -> 2018.75 | AB10: =+AB5+AB6+AB9 -> 484 | AC10: =+AC5+AC6+AC9 -> 616.5 | AD10: =+AD5+AD6+AD9 -> 543.75 | AF10: =+AF5+AF6+AF9 -> 1071 | AG10: =+AG5+AG6+AG9 -> 1224 | AH10: =+AH5+AH6+AH9 -> 1377 | AI10: =+AI5+AI6+AI9 -> 1606.5 | AJ10: =+AJ5+AJ6+AJ9 -> 0 | AL10: =+AL5+AL6+AL9 -> 484 | AM10: =+AM5+AM6+AM9 -> 616.5 | AN10: =+AN5+AN6+AN9 -> 0 | AP10: =+AP5+AP6+AP9 -> 1341 | AQ10: =+AQ5+AQ6+AQ9 -> 1611 | AR10: =+AR5+AR6+AR9 -> 1971 | AS10: =+AS5+AS6+AS9 -> 2241 | AT10: =+AT5+AT6+AT9 -> 0 | AW10: =+AW5+AW6+AW9 -> 981 | AX10: =+AX5+AX6+AX9 -> 1161 | AY10: =+AY5+AY6+AY9 -> 1251 | AZ10: =+AZ5+AZ6+AZ9 -> 1431 | BA10: =+BA5+BA6+BA9 -> 0
A12: Production cost - collection kit | B12: -9.1314238 | C12: -13.317564 | D12: -10.736757 | E12: -14.742897 | F12: -25.29023 | H12: =+C12 -> -13.317564 | I12: =+E12 -> -14.742897 | J12: =+F12 -> -25.29023 | L12: -16.0545 | M12: -21.338214 | N12: -18.742714 | O12: -23.538714 | P12: -37.503214 | R12: =+M12 -> -21.338214 | S12: =+O12 -> -23.538714 | T12: =+P12 -> -37.503214 | V12: -13.349776 | W12: -21.009253 | X12: -12.855148 | Y12: -22.829024 | Z12: -38.080772 | AB12: =+W12 -> -21.009253 | AC12: =+Y12 -> -22.829024 | AD12: =+Z12 -> -38.080772 | AF12: -8.8166333 | AG12: -18.329107 | AH12: -11.506597 | AI12: -21.01907 | AL12: =+AG12 -> -18.329107 | AM12: =+AI12 -> -21.01907 | AP12: -12.706633 | AQ12: -22.219107 | AR12: -18.996597 | AS12: -28.50907 | AW12: -12.706633 | AX12: -22.219107 | AY12: -15.396597 | AZ12: -24.90907
A13: Production cost - material | B13: -18.669504 | C13: -34.597681 | D13: -28.086762 | E13: -44.01494 | F13: -131.19746 | H13: =+C13-B13 -> -15.928178 | I13: =+E13-C13 -> -9.4172586 | J13: =+F13-E13 -> -87.182519 | L13: -34.102397 | M13: -51.921197 | N13: -52.072006 | O13: -69.890806 | P13: -172.61228 | R13: =+M13-L13 -> -17.8188 | S13: =+O13-M13 -> -17.969609 | T13: =+P13-O13 -> -102.72147 | V13: -25.930927 | W13: -35.221447 | X13: -65.498622 | Y13: -74.844126 | Z13: -210.55591 | AB13: =+W13-V13 -> -9.29052 | AC13: =+Y13-W13 -> -39.622679 | AD13: =+Z13-Y13 -> -135.71178 | AF13: -18.711553 | AG13: -34.304737 | AH13: -28.07583 | AI13: -43.669014 | AL13: =+AG13-AF13 -> -15.593184 | AM13: =+AI13-AG13 -> -9.3642772 | AP13: -18.711553 | AQ13: -34.304737 | AR13: -28.07583 | AS13: -43.669014 | AW13: -18.711553 | AX13: -34.304737 | AY13: -28.07583 | AZ13: -43.669014
A14: Production cost - examination | B14: -7.0871095 | C14: -18.647291 | D14: -7.0871095 | E14: -18.647291 | F14: -95.038958 | H14: =+B14 -> -7.0871095 | I14: =+D14 -> -7.0871095 | J14: =+F14-E14 -> -76.391667 | L14: -42.4755 | M14: -55.5515 | N14: -51.1334 | O14: -64.2094 | P14: -72.8273 | R14: =+L14 -> -42.4755 | S14: =+N14 -> -51.1334 | T14: =+P14-O14 -> -8.6179 | V14: -57.685473 | W14: -88.910657 | X14: -92.885473 | Y14: -124.11066 | Z14: -264.91066 | AB14: =+V14 -> -57.685473 | AC14: =+X14 -> -92.885473 | AD14: =+Z14-Y14 -> -140.8 | AF14: -6.4998508 | AG14: -17.073553 | AH14: -21.333184 | AI14: -31.906886 | AL14: =+AF14 -> -6.4998508 | AM14: =+AH14 -> -21.333184 | AP14: -241.10402 | AQ14: -251.67772 | AR14: -255.93735 | AS14: -266.51105 | AW14: -21.166517 | AX14: -31.740219 | AY14: -21.166517 | AZ14: -31.740219
A15: Total Production cost | B15: =SUM(B12:B14) -> -34.888037 | C15: =SUM(C12:C14) -> -66.562537 | D15: =SUM(D12:D14) -> -45.910629 | E15: =SUM(E12:E14) -> -77.405129 | F15: =SUM(F12:F14) -> -251.52665 | H15: =SUM(H12:H14) -> -36.332851 | I15: =SUM(I12:I14) -> -31.247265 | J15: =SUM(J12:J14) -> -188.86442 | L15: =SUM(L12:L14) -> -92.632397 | M15: =SUM(M12:M14) -> -128.81091 | N15: =SUM(N12:N14) -> -121.94812 | O15: =SUM(O12:O14) -> -157.63892 | P15: =SUM(P12:P14) -> -282.94279 | R15: =SUM(R12:R14) -> -81.632514 | S15: =SUM(S12:S14) -> -92.641723 | T15: =SUM(T12:T14) -> -148.84259 | V15: =SUM(V12:V14) -> -96.966177 | W15: =SUM(W12:W14) -> -145.14136 | X15: =SUM(X12:X14) -> -171.23924 | Y15: =SUM(Y12:Y14) -> -221.78381 | Z15: =SUM(Z12:Z14) -> -513.54734 | AB15: =SUM(AB12:AB14) -> -87.985245 | AC15: =SUM(AC12:AC14) -> -155.33718 | AD15: =SUM(AD12:AD14) -> -314.59255 | AF15: =SUM(AF12:AF14) -> -34.028037 | AG15: =SUM(AG12:AG14) -> -69.707396 | AH15: =SUM(AH12:AH14) -> -60.915612 | AI15: =SUM(AI12:AI14) -> -96.594971 | AJ15: =SUM(AJ12:AJ14) -> 0 | AL15: =SUM(AL12:AL14) -> -40.422141 | AM15: =SUM(AM12:AM14) -> -51.716532 | AN15: =SUM(AN12:AN14) -> 0 | AP15: =SUM(AP12:AP14) -> -272.5222 | AQ15: =SUM(AQ12:AQ14) -> -308.20156 | AR15: =SUM(AR12:AR14) -> -303.00978 | AS15: =SUM(AS12:AS14) -> -338.68914 | AT15: =SUM(AT12:AT14) -> 0 | AW15: =SUM(AW12:AW14) -> -52.584704 | AX15: =SUM(AX12:AX14) -> -88.264063 | AY15: =SUM(AY12:AY14) -> -64.638945 | AZ15: =SUM(AZ12:AZ14) -> -100.3183 | BA15: =SUM(BA12:BA14) -> 0
A17: Third party - hospitals | B17: -10.903148 | C17: -15.273333 | D17: -18.150693 | E17: -25.044563 | F17: -39.238947 | H17: =+C17-B17 -> -4.3701852 | I17: =+E17-C17 -> -9.7712294 | J17: =+F17-E17 -> -14.194385 | L17: -10.454545 | M17: -31.489362 | N17: -20.516605 | O17: -14.825737 | P17: -28.423423 | R17: =+M17-L17 -> -21.034816 | S17: =+O17-M17 -> 16.663624 | T17: =+P17-O17 -> -13.597686 | V17: =-1500/25 -> -60 | W17: =-1500/25 -> -60 | X17: =-1500/25 -> -60 | Y17: =-1500/25 -> -60 | Z17: =-1500/25 -> -60 | AB17: =+W17-V17 -> 0 | AC17: =+Y17-W17 -> 0 | AD17: =+Z17-Y17 -> 0 | AF17: -7.02 | AG17: -7.02 | AH17: -7.02 | AI17: -7.02 | AJ17: 0 | AL17: =+AG17-AF17 -> 0 | AM17: =+AI17-AG17 -> 0 | AP17: -110 | AQ17: -130 | AR17: -190 | AS17: -200
A18: Third party - collection | B18: -31.440259 | C18: -53.558175 | D18: -51.519901 | E18: -77.482966 | F18: -97.112737 | H18: =+C18-B18 -> -22.117916 | I18: =+E18-C18 -> -23.92479 | J18: =+F18-E18 -> -19.629771 | L18: -36.181818 | M18: -89.787234 | N18: -71.02583 | O18: -111.06166 | P18: -132.31609 | R18: =+M18-L18 -> -53.605416 | S18: =+O18-M18 -> -21.274428 | T18: =+P18-O18 -> -21.254424 | V18: -25.344 | W18: -36.7125 | X18: -51.127083 | Y18: -52.7 | Z18: -60 | AB18: =+W18-V18 -> -11.3685 | AC18: =+Y18-W18 -> -15.9875 | AD18: =+Z18-Y18 -> -7.3 | AF18: 0 | AG18: 0 | AH18: 0 | AI18: 0 | AJ18: 0 | AL18: =+AG18-AF18 -> 0 | AM18: =+AI18-AG18 -> 0 | AP18: 0 | AQ18: 0 | AR18: 0 | AS18: 0
A19: Third party - recruiting | B19: -32.114851 | C19: -59.337975 | D19: -49.455424 | E19: -74.590431 | F19: -181.21247 | H19: =+C19-B19 -> -27.223125 | I19: =+E19-C19 -> -15.252456 | J19: =+F19-E19 -> -106.62204 | L19: -100 | M19: -140 | N19: -190 | O19: -240 | P19: -400 | R19: =+M19-L19 -> -40 | S19: =+O19-M19 -> -100 | T19: =+P19-O19 -> -160 | V19: -12.76 | W19: -26.4 | X19: -21.45 | Y19: -24.52 | Z19: =-2000/25 -> -80 | AB19: =+W19-V19 -> -13.64 | AC19: =+Y19-W19 -> 1.88 | AD19: =+Z19-Y19 -> -55.48 | AF19: -11.472778 | AG19: -33.653481 | AH19: -20.412767 | AI19: -36.977282 | AJ19: 0 | AL19: =+AG19-AF19 -> -22.180703 | AM19: =+AI19-AG19 -> -3.3238006 | AP19: -20 | AQ19: -20 | AR19: -20 | AS19: -20
A20: Third party - other | B20: -8.1872749 | C20: -8.1872749 | D20: -8.1872749 | E20: -8.1872749 | F20: -8.1872749 | H20: =+C20-B20 -> 0 | I20: =+E20-C20 -> 0 | J20: =+F20-E20 -> 0 | L20: 0 | M20: 0 | N20: 0 | O20: 0 | P20: 0 | R20: =+M20-L20 -> 0 | S20: =+O20-M20 -> 0 | T20: =+P20-O20 -> 0 | V20: 0 | W20: 0 | X20: 0 | Y20: 0 | Z20: 0 | AB20: =+W20-V20 -> 0 | AC20: =+Y20-W20 -> 0 | AD20: =+Z20-Y20 -> 0 | AF20: 0 | AG20: 0 | AH20: 0 | AI20: 0 | AJ20: 0 | AL20: =+AG20-AF20 -> 0 | AM20: =+AI20-AG20 -> 0
A21: Total Third party cost | B21: =SUM(B17:B20) -> -82.645533 | C21: =SUM(C17:C20) -> -136.35676 | D21: =SUM(D17:D20) -> -127.31329 | E21: =SUM(E17:E20) -> -185.30523 | F21: =SUM(F17:F20) -> -325.75143 | H21: =SUM(H17:H20) -> -53.711226 | I21: =SUM(I17:I20) -> -48.948475 | J21: =SUM(J17:J20) -> -140.4462 | L21: =SUM(L17:L20) -> -146.63636 | M21: =SUM(M17:M20) -> -261.2766 | N21: =SUM(N17:N20) -> -281.54244 | O21: =SUM(O17:O20) -> -365.8874 | P21: =SUM(P17:P20) -> -560.73951 | R21: =SUM(R17:R20) -> -114.64023 | S21: =SUM(S17:S20) -> -104.6108 | T21: =SUM(T17:T20) -> -194.85211 | V21: =SUM(V17:V20) -> -98.104 | W21: =SUM(W17:W20) -> -123.1125 | X21: =SUM(X17:X20) -> -132.57708 | Y21: =SUM(Y17:Y20) -> -137.22 | Z21: =SUM(Z17:Z20) -> -200 | AB21: =SUM(AB17:AB20) -> -25.0085 | AC21: =SUM(AC17:AC20) -> -14.1075 | AD21: =SUM(AD17:AD20) -> -62.78 | AF21: =SUM(AF17:AF20) -> -18.492778 | AG21: =SUM(AG17:AG20) -> -40.673481 | AH21: =SUM(AH17:AH20) -> -27.432767 | AI21: =SUM(AI17:AI20) -> -43.997282 | AJ21: =SUM(AJ17:AJ20) -> 0 | AL21: =SUM(AL17:AL20) -> -22.180703 | AM21: =SUM(AM17:AM20) -> -3.3238006 | AN21: =SUM(AN17:AN20) -> 0 | AP21: =SUM(AP17:AP20) -> -130 | AQ21: =SUM(AQ17:AQ20) -> -150 | AR21: =SUM(AR17:AR20) -> -210 | AS21: =SUM(AS17:AS20) -> -220 | AT21: =SUM(AT17:AT20) -> 0 | AW21: =SUM(AW17:AW20) -> 0 | AX21: =SUM(AX17:AX20) -> 0 | AY21: =SUM(AY17:AY20) -> 0 | AZ21: =SUM(AZ17:AZ20) -> 0 | BA21: =SUM(BA17:BA20) -> 0
A23: Gross Margin | B23: =+B10+B15+B21 -> 953.46643 | C23: =+C10+C15+C21 -> 1021.0807 | D23: =+D10+D15+D21 -> 1203.7761 | E23: =+E10+E15+E21 -> 1343.7896 | F23: =+F10+F15+F21 -> 1441.4719 | H23: =+H10+H15+H21 -> 393.95592 | I23: =+I10+I15+I21 -> 536.30426 | J23: =+J10+J15+J21 -> 214.43939 | L23: =+L10+L15+L21 -> 831.73124 | M23: =+M10+M15+M21 -> 833.91249 | N23: =+N10+N15+N21 -> 973.50944 | O23: =+O10+O15+O21 -> 1082.9737 | P23: =+P10+P15+P21 -> 1175.0677 | R23: =+R10+R15+R21 -> 287.72725 | S23: =+S10+S15+S21 -> 419.24747 | T23: =+T10+T15+T21 -> 200.0553 | V23: =+V10+V15+V21 -> 875.92982 | W23: =+W10+W15+W21 -> 955.74614 | X23: =+X10+X15+X21 -> 1073.1837 | Y23: =+Y10+Y15+Y21 -> 1247.4962 | Z23: =+Z10+Z15+Z21 -> 1305.2027 | AB23: =+AB10+AB15+AB21 -> 371.00625 | AC23: =+AC10+AC15+AC21 -> 447.05532 | AD23: =+AD10+AD15+AD21 -> 166.37745 | AF23: =+AF10+AF15+AF21 -> 1018.4792 | AG23: =+AG10+AG15+AG21 -> 1113.6191 | AH23: =+AH10+AH15+AH21 -> 1288.6516 | AI23: =+AI10+AI15+AI21 -> 1465.9077 | AJ23: =+AJ10+AJ15+AJ21 -> 0 | AL23: =+AL10+AL15+AL21 -> 421.39716 | AM23: =+AM10+AM15+AM21 -> 561.45967 | AN23: =+AN10+AN15+AN21 -> 0 | AP23: =+AP10+AP15+AP21 -> 938.4778 | AQ23: =+AQ10+AQ15+AQ21 -> 1152.7984 | AR23: =+AR10+AR15+AR21 -> 1457.9902 | AS23: =+AS10+AS15+AS21 -> 1682.3109 | AT23: =+AT10+AT15+AT21 -> 0 | AW23: =+AW10+AW15+AW21 -> 928.4153 | AX23: =+AX10+AX15+AX21 -> 1072.7359 | AY23: =+AY10+AY15+AY21 -> 1186.3611 | AZ23: =+AZ10+AZ15+AZ21 -> 1330.6817 | BA23: =+BA10+BA15+BA21 -> 0
A24: % | B24: =+B23/B7 -> 0.75671939 | C24: =+C23/C7 -> 0.70908382 | D24: =+D23/D7 -> 0.74307165 | E24: =+E23/E7 -> 0.71099981 | F24: =+F23/F7 -> 0.60693555 | H24: =+H23/H7 -> 0.56279418 | I24: =+I23/I7 -> 0.59589362 | J24: =+J23/J7 -> 0.23826598 | L24: =+L23/L7 -> 0.66010416 | M24: =+M23/M7 -> 0.5791059 | N24: =+N23/N7 -> 0.60093176 | O24: =+O23/O7 -> 0.57300195 | P24: =+P23/P7 -> 0.49476535 | R24: =+R23/R7 -> 0.41103893 | S24: =+S23/S7 -> 0.46583053 | T24: =+T23/T7 -> 0.22228367 | V24: =+V23/V7 -> 0.6951824 | W24: =+W23/W7 -> 0.6637126 | X24: =+X23/X7 -> 0.66245906 | Y24: =+Y23/Y7 -> 0.6600509 | Z24: =+Z23/Z7 -> 0.54955902 | AB24: =+AB23/AB7 -> 0.53000894 | AC24: =+AC23/AC7 -> 0.49672814 | AD24: =+AD23/AD7 -> 0.18486383 | AF24: =+AF23/AF7 -> 0.80831681 | AG24: =+AG23/AG7 -> 0.77334661 | AH24: =+AH23/AH7 -> 0.79546396 | AI24: =+AI23/AI7 -> 0.77561256 | AJ24: =+AJ23/AJ7 -> #DIV/0! | AL24: =+AL23/AL7 -> 0.60199594 | AM24: =+AM23/AM7 -> 0.62384408 | AN24: =+AN23/AN7 -> #DIV/0! | AP24: =+AP23/AP7 -> 0.6998343 | AQ24: =+AQ23/AQ7 -> 0.71557941 | AR24: =+AR23/AR7 -> 0.73972107 | AS24: =+AS23/AS7 -> 0.7506965 | AT24: =+AT23/AT7 -> #DIV/0! | AW24: =+AW23/AW7 -> 0.94639684 | AX24: =+AX23/AX7 -> 0.92397583 | AY24: =+AY23/AY7 -> 0.94833018 | AZ24: =+AZ23/AZ7 -> 0.92989636 | BA24: =+BA23/BA7 -> #DIV/0!
A26: logistika | B26: -86.086141 | C26: -86.086141 | D26: -86.086141 | E26: -86.086141 | F26: -86.086141 | G26: pausal | H26: -86.086141 | I26: -86.086141 | J26: -86.086141 | L26: -132.52833 | M26: -132.52833 | N26: -132.52833 | O26: -132.52833 | P26: -132.52833 | Q26: vodici | R26: -132.52833 | S26: -132.52833 | T26: -132.52833 | V26: -176.50729 | W26: -176.50729 | X26: -176.50729 | Y26: -176.50729 | Z26: -176.50729 | AA26: vodici | AB26: -176.50729 | AC26: -176.50729 | AD26: -176.50729 | AF26: -120.91262 | AG26: -120.91262 | AH26: -120.91262 | AI26: -120.91262 | AK26: externe | AL26: -120.91262 | AM26: -120.91262 | AP26: -180 | AQ26: -180 | AR26: -180 | AS26: -180 | AT26: -180 | AU26: externe | AW26: -261.545 | AX26: -261.545 | AY26: -261.545 | AZ26: -261.545 | BA26: -261.545 | BB26: externe
A27: cena prace laborant priemer na produkt | B27: -149.13982 | C27: -149.13982 | D27: -149.13982 | E27: -149.13982 | F27: -149.13982 | H27: -149.13982 | I27: -149.13982 | J27: -149.13982 | L27: -140.95255 | M27: -140.95255 | N27: -140.95255 | O27: -140.95255 | P27: -140.95255 | R27: -140.95255 | S27: -140.95255 | T27: -140.95255 | V27: -263.93033 | W27: -263.93033 | X27: -263.93033 | Y27: -263.93033 | Z27: -263.93033 | AB27: -263.93033 | AC27: -263.93033 | AD27: -263.93033 | AF27: -149.13982 | AG27: -149.13982 | AH27: -149.13982 | AI27: -149.13982 | AL27: -149.13982 | AM27: -149.13982 | AP27: -149.13982 | AQ27: -149.13982 | AR27: -149.13982 | AS27: -149.13982 | AT27: -149.13982 | AW27: -149.13982 | AX27: -149.13982 | AY27: -149.13982 | AZ27: -149.13982 | BA27: -149.13982
A29: TOTAL COST | B29: =+B9+B15+B21+B26+B27 -> -541.75953 | C29: =+C9+C15+C21+C26+C27 -> -654.14526 | D29: =+D9+D15+D21+D26+D27 -> -651.44988 | E29: =+E9+E15+E21+E26+E27 -> -781.43632 | F29: =+F9+F15+F21+F26+F27 -> -1168.754 | H29: =+H9+H15+H21+H26+H27 -> -541.27004 | I29: =+I9+I15+I21+I26+I27 -> -598.9217 | J29: =+J9+J15+J21+J26+J27 -> -920.78658 | L29: =+L9+L15+L21+L26+L27 -> -701.74964 | M29: =+M9+M15+M21+M26+M27 -> -879.56838 | N29: =+N9+N15+N21+N26+N27 -> -919.97143 | O29: =+O9+O15+O21+O26+O27 -> -1080.5072 | P29: =+P9+P15+P21+P26+P27 -> -1473.4132 | R29: =+R9+R15+R21+R26+R27 -> -685.75362 | S29: =+S9+S15+S21+S26+S27 -> -754.2334 | T29: =+T9+T15+T21+T26+T27 -> -973.42557 | V29: =+V9+V15+V21+V26+V27 -> -824.5078 | W29: =+W9+W15+W21+W26+W27 -> -924.69148 | X29: =+X9+X15+X21+X26+X27 -> -987.25395 | Y29: =+Y9+Y15+Y21+Y26+Y27 -> -1082.9414 | Z29: =+Z9+Z15+Z21+Z26+Z27 -> -1510.235 | AB29: =+AB9+AB15+AB21+AB26+AB27 -> -769.43137 | AC29: =+AC9+AC15+AC21+AC26+AC27 -> -893.3823 | AD29: =+AD9+AD15+AD21+AD26+AD27 -> -1174.0602 | AF29: =+AF9+AF15+AF21+AF26+AF27 -> -511.57325 | AG29: =+AG9+AG15+AG21+AG26+AG27 -> -596.43331 | AH29: =+AH9+AH15+AH21+AH26+AH27 -> -601.40082 | AI29: =+AI9+AI15+AI21+AI26+AI27 -> -694.14469 | AJ29: =+AJ9+AJ15+AJ21+AJ26+AJ27 -> 0 | AL29: =+AL9+AL15+AL21+AL26+AL27 -> -548.65528 | AM29: =+AM9+AM15+AM21+AM26+AM27 -> -608.59277 | AN29: =+AN9+AN15+AN21+AN26+AN27 -> 0 | AP29: =+AP9+AP15+AP21+AP26+AP27 -> -731.66202 | AQ29: =+AQ9+AQ15+AQ21+AQ26+AQ27 -> -787.34138 | AR29: =+AR9+AR15+AR21+AR26+AR27 -> -842.1496 | AS29: =+AS9+AS15+AS21+AS26+AS27 -> -887.82896 | AT29: =+AT9+AT15+AT21+AT26+AT27 -> -329.13982 | AW29: =+AW9+AW15+AW21+AW26+AW27 -> -463.26952 | AX29: =+AX9+AX15+AX21+AX26+AX27 -> -498.94888 | AY29: =+AY9+AY15+AY21+AY26+AY27 -> -475.32377 | AZ29: =+AZ9+AZ15+AZ21+AZ26+AZ27 -> -511.00312 | BA29: =+BA9+BA15+BA21+BA26+BA27 -> -410.68482
V31: =+V15+V27 -> -360.8965 | AC31: =+AC15+AC27 -> -419.2675

Sheet Sheet1
A1: Failed Collection or Contamination
A3: Product | B3: CB* | C3: PB | D3: T (CB) | E3: T (PB) | F3: PL | G3: Classic | H3: Premium | I3: Classic+T | J3: Premium+T | K3: Placenta | L3: Discounted | M3: Product
A4: Price | B4: =+G4 -> 1400 | C4: =+H4-G4 -> 200 | D4: =+I4-B4 -> 400 | E4: =+J4-H4 -> 500 | F4: =+K4-J4 -> 400 | G4: 1400 | H4: 1600 | I4: 1800 | J4: 2100 | K4: 2500 | L4: price | M4: adjustment
A5: ALL PRODUCS | B5: FALSE | C5: FALSE | D5: FALSE | E5: FALSE | F5: FALSE | G5: x | H5: x | I5: x | J5: x | K5: x | L5: 1 | M5: VIP
A6: Classic | B6: TRUE | C6: FALSE | D6: FALSE | E6: FALSE | F6: FALSE | G6: =+G4 -> 1400 | H6: x | I6: x | J6: x | K6: x | L6: =+B4 -> 1400 | M6: Classic
A7: Premium | B7: TRUE | C7: TRUE | D7: FALSE | E7: FALSE | F7: FALSE | G7: x | H7: =+H4 -> 1600 | I7: x | J7: x | K7: x | L7: =+B4+C4 -> 1600 | M7: Premium
A8: Premium | B8: TRUE | C8: FALSE | D8: FALSE | E8: FALSE | F8: FALSE | G8: x | H8: =+H7 -> 1600 | I8: x | J8: x | K8: x | L8: =+B4 -> 1400 | M8: Classic
A9: Premium | B9: FALSE | C9: TRUE | D9: FALSE | E9: FALSE | F9: FALSE | G9: x | H9: =+H8 -> 1600 | I9: x | J9: x | K9: x | L9: =+C4 -> 200 | M9: PB
A10: Classic+Tissue | B10: TRUE | C10: FALSE | D10: TRUE | E10: FALSE | F10: FALSE | G10: x | H10: x | I10: =+I4 -> 1800 | J10: x | K10: x | L10: =+B4+D4 -> 1800 | M10: Classic+Tissue
A11: Classic+Tissue | B11: TRUE | C11: FALSE | D11: FALSE | E11: FALSE | F11: FALSE | G11: x | H11: x | I11: =+I10 -> 1800 | J11: x | K11: x | L11: =+B4 -> 1400 | M11: Classic
A12: Classic+Tissue | B12: FALSE | C12: FALSE | D12: TRUE | E12: FALSE | F12: FALSE | G12: x | H12: x | I12: =+I11 -> 1800 | J12: x | K12: x | L12: =+D4 -> 400 | M12: T (CB)
A13: Premium+Tissue | B13: TRUE | C13: TRUE | D13: TRUE | E13: FALSE | F13: FALSE | G13: x | H13: x | I13: x | J13: =+J4 -> 2100 | K13: x | L13: =+B4+C4+E4 -> 2100 | M13: Premium+Tissue
A14: Premium+Tissue | B14: TRUE | C14: FALSE | D14: FALSE | E14: FALSE | F14: FALSE | G14: x | H14: x | I14: x | J14: =+J13 -> 2100 | K14: x | L14: =+B4 -> 1400 | M14: Classic
A15: Premium+Tissue | B15: TRUE | C15: TRUE | D15: FALSE | E15: FALSE | F15: FALSE | G15: x | H15: x | I15: x | J15: =+J14 -> 2100 | K15: x | L15: =+B4+C4 -> 1600 | M15: Premium
A16: Premium+Tissue | B16: TRUE | C16: FALSE | D16: TRUE | E16: FALSE | F16: FALSE | G16: x | H16: x | I16: x | J16: =+J15 -> 2100 | K16: x | L16: =+B4+D4 -> 1800 | M16: Classic+Tissue
A17: Premium+Tissue | B17: FALSE | C17: TRUE | D17: FALSE | E17: FALSE | F17: FALSE | G17: x | H17: x | I17: x | J17: =+J16 -> 2100 | K17: x | L17: =+C4 -> 200 | M17: PB
A18: Premium+Tissue | B18: FALSE | C18: TRUE | D18: FALSE | E18: TRUE | F18: FALSE | G18: x | H18: x | I18: x | J18: =+J17 -> 2100 | K18: x | L18: =+E4+C4 -> 700 | M18: PB+T (PB)
A19: Premium+Tissue | B19: FALSE | C19: FALSE | D19: FALSE | E19: TRUE | F19: FALSE | G19: x | H19: x | I19: x | J19: =+J18 -> 2100 | K19: x | L19: =+E4 -> 500 | M19: T (PB)
A20: PLACENTA | B20: TRUE | C20: TRUE | D20: FALSE | E20: TRUE | F20: TRUE | G20: x | H20: x | I20: x | J20: x | K20: =+K4 -> 2500 | L20: =+B4+C4+E4+F4 -> 2500 | M20: Placenta
A21: PLACENTA | B21: TRUE | C21: FALSE | D21: FALSE | E21: FALSE | F21: FALSE | G21: x | H21: x | I21: x | J21: x | K21: =+K20 -> 2500 | L21: =+B4 -> 1400 | M21: Classic
A22: PLACENTA | B22: TRUE | C22: TRUE | D22: FALSE | E22: FALSE | F22: FALSE | G22: x | H22: x | I22: x | J22: x | K22: =+K21 -> 2500 | L22: =+B4+C4 -> 1600 | M22: Premium
A23: PLACENTA | B23: TRUE | C23: TRUE | D23: FALSE | E23: TRUE | F23: FALSE | G23: x | H23: x | I23: x | J23: x | K23: =+K22 -> 2500 | L23: =+B4+C4+E4 -> 2100 | M23: Premium+Tissue
A24: PLACENTA | B24: TRUE | C24: FALSE | D24: TRUE | E24: FALSE | F24: FALSE | G24: x | H24: x | I24: x | J24: x | K24: =+K23 -> 2500 | L24: =+B4+D4 -> 1800 | M24: Classic+Tissue
A25: PLACENTA | B25: FALSE | C25: TRUE | D25: FALSE | E25: FALSE | F25: FALSE | G25: x | H25: x | I25: x | J25: x | K25: =+K24 -> 2500 | L25: =+C4 -> 200 | M25: PB
A26: PLACENTA | B26: FALSE | C26: TRUE | D26: FALSE | E26: TRUE | F26: FALSE | G26: x | H26: x | I26: x | J26: x | K26: =+K25 -> 2500 | L26: =+C4+E4 -> 700 | M26: PB+T (PB)
A27: PLACENTA | B27: FALSE | C27: FALSE | D27: FALSE | E27: TRUE | F27: FALSE | G27: x | H27: x | I27: x | J27: x | K27: =+K26 -> 2500 | L27: =+E4 -> 500 | M27: T (PB)
A28: PLACENTA | B28: FALSE | C28: FALSE | D28: FALSE | E28: FALSE | F28: TRUE | G28: x | H28: x | I28: x | J28: x | K28: =+K27 -> 2500 | L28: =+F4 -> 400 | M28: PL
A29: PLACENTA | B29: TRUE | C29: FALSE | D29: FALSE | E29: FALSE | F29: TRUE | G29: x | H29: x | I29: x | J29: x | K29: =+K28 -> 2500 | L29: =+B4+F4 -> 1800 | M29: CB+PL
A30: PLACENTA | B30: TRUE | C30: TRUE | D30: FALSE | E30: FALSE | F30: TRUE | G30: x | H30: x | I30: x | J30: x | K30: =+K29 -> 2500 | L30: =+B4+C4+F4 -> 2000 | M30: CB+PB+PL
A31: PLACENTA | B31: TRUE | C31: FALSE | D31: FALSE | E31: TRUE | F31: TRUE | G31: x | H31: x | I31: x | J31: x | K31: =+K30 -> 2500 | L31: =+B4+E4+F4 -> 2300 | M31: CB+T(PB)+PL
A32: PLACENTA | B32: FALSE | C32: TRUE | D32: FALSE | E32: FALSE | F32: TRUE | G32: x | H32: x | I32: x | J32: x | K32: =+K31 -> 2500 | L32: =+C4+F4 -> 600 | M32: PB+PL
A33: PLACENTA | B33: FALSE | C33: TRUE | D33: FALSE | E33: TRUE | F33: TRUE | G33: x | H33: x | I33: x | J33: x | K33: =+K32 -> 2500 | L33: =+C4+E4+F4 -> 1100 | M33: PB+T(PB)+PL
A34: PLACENTA | B34: FALSE | C34: FALSE | D34: FALSE | E34: TRUE | F34: TRUE | G34: x | H34: x | I34: x | J34: x | K34: =+K33 -> 2500 | L34: =+E4+F4 -> 900 | M34: T(PB)+PL
A35: * collection CB <20ml = discount 500 EUR
